[
  {
    "SurahNumber": "82",
    "AyahFrom": "0",
    "AyahTo": "0",
    "AyahText": " Introduction to Infitaar ",
    "Text": "<note id=\"1\">\r\\n<div class=\"title\">Which was revealed in Makkah</div>\r\\n\\t\\t\\t\\t<div class=\"title\">The Virtues of Surat Al-Infitar</div>\r\\n<p>An-Nasa'i recorded from Jabir that Mu`adh stood and lead the people in the Night prayer, and he made the recitation of his prayer long. So the Prophet said,</p>\r\\n<p dir=\"rtl\"><div class=\"arabic_text_style\" align=\"right\" dir=\"rtl\">&laquo;&#1571;&#1614;&#1601;&#1614;&#1578;&#1617;&#1614;&#1575;&#1606;&#1612; &#1571;&#1614;&#1606;&#1618;&#1578;&#1614; &#1610;&#1614;&#1575; &#1605;&#1615;&#1593;&#1614;&#1575;&#1584;&#1615;&#1567; &#1571;&#1614;&#1610;&#1618;&#1606;&#1614; &#1603;&#1615;&#1606;&#1618;&#1578;&#1614; &#1593;&#1614;&#1606;&#1618;</div></p>\r\\n<p dir=\"rtl\"><div class=\"arabic_text_style\" align=\"right\" dir=\"rtl\">&#64831;&#1587;&#1614;&#1576;&#1617;&#1616;&#1581;&#1616; &#1575;&#1587;&#1618;&#1605;&#1614; &#1585;&#1614;&#1576;&#1617;&#1616;&#1603;&#1614; &#1575;&#1604;&#1575;&#1617;&#1593;&#1618;&#1604;&#1614;&#1609; &#64830;</div></p>\r\\n<p dir=\"rtl\"><div class=\"arabic_text_style\" align=\"right\" dir=\"rtl\">&#64831;&#1608;&#1614;&#1575;&#1604;&#1590;&#1617;&#1615;&#1581;&#1614;&#1609; &#64830;</div></p>\r\\n<p dir=\"rtl\"><div class=\"arabic_text_style\" align=\"right\" dir=\"rtl\">&#1608;&#1614;</div></p>\r\\n<p dir=\"rtl\"><div class=\"arabic_text_style\" align=\"right\" dir=\"rtl\">&#64831;&#1573;&#1616;&#1584;&#1614;&#1575; &#1575;&#1604;&#1587;&#1617;&#1614;&#1605;&#1614;&#1570;&#1569;&#1615; &#1575;&#1606;&#1601;&#1614;&#1591;&#1614;&#1585;&#1614;&#1578;&#1618; &#64830;&raquo;</div></p>\r\\n<p>(Are you putting the people to trial O Mu`adh Why don't you recite (Glorify the Name of your Lord the Most High) (87), (By the forenoon) (93), and (When the heaven is cleft asunder) (82))'' The basis of this Hadith is found in the Two Sahihs, however the mentioning of</p>\r\\n<p dir=\"rtl\"><div class=\"arabic_text_style\" align=\"right\" dir=\"rtl\">&#64831;&#1573;&#1616;&#1584;&#1614;&#1575; &#1575;&#1604;&#1587;&#1617;&#1614;&#1605;&#1614;&#1570;&#1569;&#1615; &#1575;&#1606;&#1601;&#1614;&#1591;&#1614;&#1585;&#1614;&#1578;&#1618; &#64830;</div></p>\r\\n<p>(When the heaven is cleft asunder.) has only been mentioned by An-Nasa'i. It has been previously mentioned in a narration from `Abdullah bin `Umar that the Prophet said,</p>\r\\n<p dir=\"rtl\"><div class=\"arabic_text_style\" align=\"right\" dir=\"rtl\">&laquo;&#1605;&#1614;&#1606;&#1618; &#1587;&#1614;&#1585;&#1617;&#1614;&#1607;&#1615; &#1571;&#1614;&#1606;&#1618; &#1610;&#1614;&#1606;&#1618;&#1592;&#1615;&#1585;&#1614; &#1573;&#1616;&#1604;&#1614;&#1609; &#1575;&#1604;&#1618;&#1602;&#1616;&#1610;&#1614;&#1575;&#1605;&#1614;&#1577;&#1616; &#1585;&#1614;&#1571;&#1618;&#1610;&#1614; &#1593;&#1614;&#1610;&#1618;&#1606;&#1613; &#1601;&#1614;&#1604;&#1618;&#1610;&#1614;&#1602;&#1618;&#1585;&#1614;&#1571;&#1618;:</div></p>\r\\n<p dir=\"rtl\"><div class=\"arabic_text_style\" align=\"right\" dir=\"rtl\">&#64831;&#1573;&#1616;&#1584;&#1614;&#1575; &#1575;&#1604;&#1588;&#1617;&#1614;&#1605;&#1618;&#1587;&#1615; &#1603;&#1615;&#1608;&#1617;&#1616;&#1585;&#1614;&#1578;&#1618; &#64830;</div></p>\r\\n<p>&#1608;</p>\r\\n<p dir=\"rtl\"><div class=\"arabic_text_style\" align=\"right\" dir=\"rtl\">&#64831;&#1573;&#1616;&#1584;&#1614;&#1575; &#1575;&#1604;&#1587;&#1617;&#1614;&#1605;&#1614;&#1570;&#1569;&#1615; &#1575;&#1606;&#1601;&#1614;&#1591;&#1614;&#1585;&#1614;&#1578;&#1618; &#64830;</div></p>\r\\n<p dir=\"rtl\"><div class=\"arabic_text_style\" align=\"right\" dir=\"rtl\">&#1608;</div></p>\r\\n<p dir=\"rtl\"><div class=\"arabic_text_style\" align=\"right\" dir=\"rtl\">&#64831;&#1573;&#1616;&#1584;&#1614;&#1575; &#1575;&#1604;&#1587;&#1617;&#1614;&#1605;&#1614;&#1570;&#1569;&#1615; &#1575;&#1606;&#1588;&#1614;&#1602;&#1617;&#1614;&#1578;&#1618; &#64830;&raquo;</div></p>\r\\n<p>(Whoever would be pleased to look at the Day of Resurrection with his own eyes, then let him recite, (When the sun is Kuwwirat.) (81) and; (When the heaven is cleft asunder) (82) and; (When the heaven is split asunder) (84).)</p>\r\\n<p dir=\"rtl\"><div class=\"arabic_text_style\" align=\"right\" dir=\"rtl\">\r\\n&#64831;&#1576;&#1616;&#1587;&#1618;&#1605;&#1616; &#1575;&#1604;&#1604;&#1617;&#1614;&#1607;&#1616; &#1575;&#1604;&#1585;&#1617;&#1614;&#1581;&#1618;&#1605;&#1614;&#1600;&#1606;&#1616; &#1575;&#1604;&#1585;&#1617;&#1614;&#1581;&#1616;&#1610;&#1605;&#1616;</div></p>\r\\n<p>(In the Name of Allah, the Most Gracious, the Most Merciful.</p>\r\\n\r\\n\\t\\t\\t</note>"
  },
  {
    "SurahNumber": "82",
    "AyahFrom": "1",
    "AyahTo": "12",
    "AyahText": " <p dir=\"rtl\"><div class=\"arabic_text_style\" align=\"right\" dir=\"rtl\">&#1603;&#1614;&#1604;&#1575;&#1617;&#1614; &#1576;&#1614;&#1604;&#1618; &#1578;&#1615;&#1603;&#1614;&#1584;&#1617;&#1576;&#1615;&#1608;&#1606;&#1614; &#1576;&#1616;&#1575;&#1604;&#1583;&#1617;&#1610;&#1606;&#1616;- &#1608;&#1614;&#1573;&#1616;&#1606;&#1617;&#1614; &#1593;&#1614;&#1604;&#1614;&#1610;&#1618;&#1603;&#1615;&#1605;&#1618; &#1604;&#1614;&#1581;&#1614;&#1600;&#1601;&#1616;&#1592;&#1616;&#1610;&#1606;&#1614;- &#1603;&#1616;&#1585;&#1614;&#1575;&#1605;&#1575;&#1611; &#1603;&#1614;&#1600;&#1578;&#1616;&#1576;&#1616;&#1610;&#1606;&#1614;- &#1610;&#1614;&#1593;&#1618;&#1604;&#1614;&#1605;&#1615;&#1608;&#1606;&#1614; &#1605;&#1614;&#1575; &#1578;&#1614;&#1601;&#1618;&#1593;&#1614;&#1604;&#1615;&#1608;&#1606;&#1614;-</div></p>\\n<i><p><b>1.</b> When the heaven is cleft asunder (Infatarat). <b>2.</b> And when the stars Intatharat. <b>3.</b> And when the seas Fujjirat. <b>4.</b> And when the graves Bu`thirat. <b>5.</b> A person will know what he has sent forward and left behind. <b>6.</b> O man! What has made you careless about your Lord, the Most Generous <b>7.</b> Who created you, fashioned you perfectly, and gave you due proportion. <b>8.</b> In whatever form He willed, He put you together. <b>9.</b> Nay! But you deny (the Day of) Ad-Din. <b>10.</b> But verily, over you to watch you <b>11.</b> Kiraman Katibin, <b>12.</b> They know all that you do.) What will happen on the Day of Judgement Allah says,</p></i> \\n",
    "Text": "<note id=\"2\">\\n\\t\\t\\t\\t<p dir=\"rtl\"><div class=\"arabic_text_style\" align=\"right\" dir=\"rtl\">&#64831;&#1573;&#1616;&#1584;&#1614;&#1575; &#1575;&#1604;&#1587;&#1617;&#1614;&#1605;&#1614;&#1570;&#1569;&#1615; &#1575;&#1606;&#1601;&#1614;&#1591;&#1614;&#1585;&#1614;&#1578;&#1618; &#64830;</div></p>\\n<p>(When the heaven is cleft asunder (Infatarat).) meaning, it splits. This is as Allah says,</p>\\n<p dir=\"rtl\"><div class=\"arabic_text_style\" align=\"right\" dir=\"rtl\">&#64831;&#1575;&#1604;&#1587;&#1617;&#1614;&#1605;&#1614;&#1570;&#1569;&#1615; &#1605;&#1615;&#1606;&#1601;&#1614;&#1591;&#1616;&#1585;&#1612; &#1576;&#1616;&#1607;&#1616;&#64830;</div></p>\\n<p>(Whereon the heaven will be cleft asunder (Munfatir)) (73:18) Then Allah says,</p>\\n<p dir=\"rtl\"><div class=\"arabic_text_style\" align=\"right\" dir=\"rtl\">&#64831;&#1608;&#1614;&#1573;&#1616;&#1584;&#1614;&#1575; &#1575;&#1604;&#1618;&#1603;&#1614;&#1608;&#1614;&#1575;&#1603;&#1616;&#1576;&#1615; &#1575;&#1606;&#1578;&#1614;&#1579;&#1614;&#1585;&#1614;&#1578;&#1618; &#64830;</div></p>\\n<p>(And when the stars Intatharat.) meaning, fallen.</p>\\n<p dir=\"rtl\"><div class=\"arabic_text_style\" align=\"right\" dir=\"rtl\">&#64831;&#1608;&#1614;&#1573;&#1616;&#1584;&#1614;&#1575; &#1575;&#1604;&#1618;&#1576;&#1616;&#1581;&#1614;&#1575;&#1585;&#1615; &#1601;&#1615;&#1580;&#1617;&#1616;&#1585;&#1614;&#1578;&#1618; &#64830;</div></p>\\n<p>(And when the seas Fujjirat.) `Ali bin Abi Talhah reported from Ibn `Abbas that he said, &quot;Allah will cause some of it to burst forth over other parts of it.'' Al-Hasan said, &quot;Allah will cause some parts of it to burst forth over other parts of it, and its water will go away.'' Qatadah said, &quot;Its fresh water will mix with its salt water.''</p>\\n<p dir=\"rtl\"><div class=\"arabic_text_style\" align=\"right\" dir=\"rtl\">&#64831;&#1608;&#1614;&#1573;&#1616;&#1584;&#1614;&#1575; &#1575;&#1604;&#1618;&#1602;&#1615;&#1576;&#1615;&#1608;&#1585;&#1615; &#1576;&#1615;&#1593;&#1618;&#1579;&#1616;&#1585;&#1614;&#1578;&#1618; &#64830;</div></p>\\n<p>(And when the graves Bu`thirat.) Ibn `Abbas said, &quot;searched.'' As-Suddi said, &quot;Tub`athiru means that they will be moved and those who are in them will come out.''</p>\\n<p dir=\"rtl\"><div class=\"arabic_text_style\" align=\"right\" dir=\"rtl\">&#64831;&#1593;&#1614;&#1604;&#1616;&#1605;&#1614;&#1578;&#1618; &#1606;&#1614;&#1601;&#1618;&#1587;&#1612; &#1605;&#1617;&#1614;&#1575; &#1602;&#1614;&#1583;&#1617;&#1614;&#1605;&#1614;&#1578;&#1618; &#1608;&#1614;&#1571;&#1614;&#1582;&#1617;&#1614;&#1585;&#1614;&#1578;&#1618; &#64830;</div></p>\\n<p>(A person will know what he has sent forward and left behind.) meaning, when this happens then this will occur. Mankind should not forget about Allah Allah says,</p>\\n<p dir=\"rtl\"><div class=\"arabic_text_style\" align=\"right\" dir=\"rtl\">&#64831;&#1610;&#1571;&#1614;&#1610;&#1617;&#1615;&#1607;&#1614;&#1575; &#1575;&#1604;&#1573;&#1616;&#1606;&#1587;&#1614;&#1600;&#1606;&#1615; &#1605;&#1614;&#1575; &#1594;&#1614;&#1585;&#1617;&#1614;&#1603;&#1614; &#1576;&#1616;&#1585;&#1614;&#1576;&#1617;&#1616;&#1603;&#1614; &#1575;&#1604;&#1618;&#1603;&#1614;&#1585;&#1616;&#1610;&#1605;&#1616; &#64830;</div></p>\\n<p>(O man! What has made you careless about your Lord, the Most Generous) This is a threat. It is not an attempt to get a reply as some people mistakenly think. They consider it as if the Most Generous is asking them so that they will say, &quot;His honor deceived him (or made him careless of his Lord).'' rather the meaning of this Ayah is, &quot;O Son of Adam! What has deceived you from your Lord, the Most Generous -- meaning the Most Great -- so that you went forth disobeying Him, and you met Him with that which was unbefitting.'' This is similar to what has been reported in the Hadith,</p>\\n<p dir=\"rtl\"><div class=\"arabic_text_style\" align=\"right\" dir=\"rtl\">&laquo;&#1610;&#1614;&#1602;&#1615;&#1608;&#1604;&#1615; &#1575;&#1604;&#1604;&#1607;&#1615; &#1578;&#1614;&#1593;&#1614;&#1575;&#1604;&#1614;&#1609; &#1610;&#1614;&#1608;&#1618;&#1605;&#1614; &#1575;&#1604;&#1618;&#1602;&#1616;&#1610;&#1614;&#1575;&#1605;&#1614;&#1577;&#1616;: &#1610;&#1614;&#1575; &#1575;&#1576;&#1618;&#1606;&#1614; &#1570;&#1583;&#1614;&#1605;&#1614; &#1605;&#1614;&#1575; &#1594;&#1614;&#1585;&#1617;&#1614;&#1603;&#1614; &#1576;&#1616;&#1610;&#1567; &#1610;&#1614;&#1575; &#1575;&#1576;&#1618;&#1606;&#1614; &#1570;&#1583;&#1614;&#1605;&#1614; &#1605;&#1614;&#1575;&#1584;&#1614;&#1575; &#1571;&#1614;&#1580;&#1614;&#1576;&#1618;&#1578;&#1614; &#1575;&#1604;&#1618;&#1605;&#1615;&#1585;&#1618;&#1587;&#1614;&#1604;&#1616;&#1610;&#1606;&#1614;&#1567;&raquo;</div></p>\\n<p>(Allah will say on the Day of Judgement: &quot;O Son of Adam! What has deceived you concerning Me O Son of Adam What was your response to the Messengers'') Al-Baghawi mentioned that Al-Kalbi and Muqatil said, &quot;This Ayah was revealed about Al-Aswad bin Shariq who struck the Prophet and he was not punished in retaliation. So Allah revealed,</p>\\n<p dir=\"rtl\"><div class=\"arabic_text_style\" align=\"right\" dir=\"rtl\">&#64831;&#1605;&#1614;&#1575; &#1594;&#1614;&#1585;&#1617;&#1614;&#1603;&#1614; &#1576;&#1616;&#1585;&#1614;&#1576;&#1617;&#1616;&#1603;&#1614; &#1575;&#1604;&#1618;&#1603;&#1614;&#1585;&#1616;&#1610;&#1605;&#1616;&#64830;</div></p>\\n<p>(What has made you careless about your Lord, the Most Generous)'' Then Allah said,</p>\\n<p dir=\"rtl\"><div class=\"arabic_text_style\" align=\"right\" dir=\"rtl\">&#64831;&#1575;&#1604;&#1617;&#1614;&#1584;&#1616;&#1609; &#1582;&#1614;&#1604;&#1614;&#1602;&#1614;&#1603;&#1614; &#1601;&#1614;&#1587;&#1614;&#1608;&#1617;&#1614;&#1575;&#1603;&#1614; &#1601;&#1614;&#1593;&#1614;&#1583;&#1614;&#1604;&#1614;&#1603;&#1614; &#64830;</div></p>\\n<p>(Who created you, fashioned you perfectly, and gave you due proportion.) meaning, `what has deceived you concerning the Most Generous Lord'</p>\\n<p dir=\"rtl\"><div class=\"arabic_text_style\" align=\"right\" dir=\"rtl\">&#64831;&#1575;&#1604;&#1617;&#1614;&#1584;&#1616;&#1609; &#1582;&#1614;&#1604;&#1614;&#1602;&#1614;&#1603;&#1614; &#1601;&#1614;&#1587;&#1614;&#1608;&#1617;&#1614;&#1575;&#1603;&#1614; &#1601;&#1614;&#1593;&#1614;&#1583;&#1614;&#1604;&#1614;&#1603;&#1614; &#64830;</div></p>\\n<p>(Who created you, fashioned you perfectly, and gave you due proportion.) meaning, `He made you complete, straight, and perfectly balanced and proportioned in stature. He fashioned you in the best of forms and shapes.' Imam Ahmad recorded from Busr bin Jahhash Al-Qurashi that one day the Messenger of Allah spat in his palm and placed his finger on it. Then he said,</p>\\n<p dir=\"rtl\"><div class=\"arabic_text_style\" align=\"right\" dir=\"rtl\">&laquo;&#1602;&#1614;&#1575;&#1604;&#1614; &#1575;&#1604;&#1604;&#1607;&#1615; &#1593;&#1614;&#1586;&#1617;&#1614; &#1608;&#1614;&#1580;&#1614;&#1604;&#1617;&#1614;: &#1610;&#1614;&#1575; &#1575;&#1576;&#1618;&#1606;&#1614; &#1570;&#1583;&#1614;&#1605;&#1614; &#1571;&#1614;&#1606;&#1618;&#1609; &#1578;&#1615;&#1593;&#1618;&#1580;&#1616;&#1586;&#1615;&#1606;&#1616;&#1610; &#1608;&#1614;&#1602;&#1614;&#1583;&#1618; &#1582;&#1614;&#1604;&#1614;&#1602;&#1618;&#1578;&#1615;&#1603;&#1614; &#1605;&#1616;&#1606;&#1618; &#1605;&#1616;&#1579;&#1618;&#1604;&#1616; &#1607;&#1584;&#1616;&#1607;&#1616;&#1567; &#1581;&#1614;&#1578;&#1618;&#1609; &#1573;&#1616;&#1584;&#1614;&#1575; &#1587;&#1614;&#1608;&#1617;&#1614;&#1610;&#1618;&#1578;&#1615;&#1603;&#1614; &#1608;&#1614;&#1593;&#1614;&#1583;&#1614;&#1604;&#1618;&#1578;&#1615;&#1603;&#1614; &#1605;&#1614;&#1588;&#1614;&#1610;&#1618;&#1578;&#1614; &#1576;&#1614;&#1610;&#1618;&#1606;&#1614; &#1576;&#1615;&#1585;&#1618;&#1583;&#1614;&#1610;&#1618;&#1606;&#1616;&#1548; &#1608;&#1614;&#1604;&#1616;&#1604;&#1618;&#1571;&#1614;&#1585;&#1618;&#1590;&#1616; &#1605;&#1616;&#1606;&#1618;&#1603;&#1614; &#1608;&#1614;&#1574;&#1616;&#1610;&#1583;&#1612;&#1548; &#1601;&#1614;&#1580;&#1614;&#1605;&#1614;&#1593;&#1618;&#1578;&#1614; &#1608;&#1614;&#1605;&#1614;&#1606;&#1614;&#1593;&#1618;&#1578;&#1614; &#1581;&#1614;&#1578;&#1618;&#1609; &#1573;&#1616;&#1584;&#1614;&#1575; &#1576;&#1614;&#1604;&#1614;&#1594;&#1614;&#1578;&#1616; &#1575;&#1604;&#1578;&#1617;&#1614;&#1585;&#1614;&#1575;&#1602;&#1616;&#1610;&#1614; &#1602;&#1615;&#1604;&#1618;&#1578;&#1614;: &#1571;&#1614;&#1578;&#1614;&#1589;&#1614;&#1583;&#1617;&#1614;&#1602;&#1615; &#1608;&#1614;&#1571;&#1614;&#1606;&#1617;&#1614;&#1609; &#1571;&#1614;&#1608;&#1614;&#1575;&#1606;&#1615; &#1575;&#1604;&#1589;&#1617;&#1614;&#1583;&#1614;&#1602;&#1614;&#1577;&#1616;&#1567;&raquo;</div></p>\\n<p>(Allah the Mighty and Sublime says: &quot;O Son of Adam! How can you escape Me when I created you from something similar to this (spit) Then I fashioned you and made your creation balanced so that you walked between the two outer garments. And the earth has a burial place for you. So you gathered (wealth) and withheld it until your soul reached your collarbone (i.e., death comes). Then, at that time you say, `I will give charity now.' But how will there be time for charity'') This Hadith has also been recorded by Ibn Majah . Concerning Allah's statement,</p>\\n<p dir=\"rtl\"><div class=\"arabic_text_style\" align=\"right\" dir=\"rtl\">&#64831;&#1601;&#1616;&#1609; &#1571;&#1614;&#1609;&#1617;&#1616; &#1589;&#1615;&#1608;&#1585;&#1614;&#1577;&#1613; &#1605;&#1617;&#1614;&#1575; &#1588;&#1614;&#1570;&#1569;&#1614; &#1585;&#1614;&#1603;&#1617;&#1614;&#1576;&#1614;&#1603;&#1614; &#64830;</div></p>\\n<p>(In whatever form He willed, He put you together.) Mujahid said, &quot;In which resemblance: the father, the mother, the paternal uncle, or the maternal uncle.'' In the Two Sahihs it is recorded from Abu Hurayrah that a man said, &quot;O Messenger of Allah! Verily, my wife has given birth to a black boy.'' The Prophet said,</p>\\n<p dir=\"rtl\"><div class=\"arabic_text_style\" align=\"right\" dir=\"rtl\">&laquo;&#1607;&#1614;&#1604;&#1618; &#1604;&#1614;&#1603;&#1614; &#1605;&#1616;&#1606;&#1618; &#1573;&#1616;&#1576;&#1616;&#1604;&#1613;&#1567;&raquo;</div></p>\\n<p>(Do you have any camels) The man said, &quot;Yes.'' The Prophet then said,</p>\\n<p dir=\"rtl\"><div class=\"arabic_text_style\" align=\"right\" dir=\"rtl\">&laquo;&#1601;&#1614;&#1605;&#1614;&#1575; &#1571;&#1614;&#1604;&#1618;&#1608;&#1614;&#1575;&#1606;&#1615;&#1607;&#1614;&#1575;&raquo;</div></p>\\n<p>(What color are they) The man said, &quot;Red.'' The Prophet said,</p>\\n<p dir=\"rtl\"><div class=\"arabic_text_style\" align=\"right\" dir=\"rtl\">&laquo;&#1601;&#1614;&#1607;&#1614;&#1604;&#1618; &#1601;&#1616;&#1610;&#1607;&#1614;&#1575; &#1605;&#1616;&#1606;&#1618; &#1571;&#1614;&#1608;&#1618;&#1585;&#1614;&#1602;&raquo;</div></p>\\n<p>(Do any of them have patches of gray) The man said, &quot;Yes.'' The Prophet asked him,</p>\\n<p dir=\"rtl\"><div class=\"arabic_text_style\" align=\"right\" dir=\"rtl\">&laquo;&#1601;&#1614;&#1571;&#1614;&#1606;&#1618;&#1609; &#1571;&#1614;&#1578;&#1614;&#1575;&#1607;&#1614;&#1575; &#1584;&#1604;&#1616;&#1603;&raquo;</div></p>\\n<p>(How did this happen to them) The man replied, &quot;It is probably an inherited genetical strain.'' The Prophet then said,</p>\\n<p dir=\"rtl\"><div class=\"arabic_text_style\" align=\"right\" dir=\"rtl\">&laquo;&#1608;&#1614;&#1607;&#1614;&#1584;&#1614;&#1575; &#1593;&#1614;&#1587;&#1614;&#1609; &#1571;&#1614;&#1606;&#1618; &#1610;&#1614;&#1603;&#1615;&#1608;&#1606;&#1614; &#1606;&#1614;&#1586;&#1614;&#1593;&#1614;&#1607;&#1615; &#1593;&#1616;&#1585;&#1618;&#1602;&raquo;</div></p>\\n<p>(Likewise, this (with your son) is probably an inherited genetical strain.) The Cause of Deception and alerting to the Fact that Angels record the Deeds of the Children of Adam Concerning Allah's statement,</p>\\n<p dir=\"rtl\"><div class=\"arabic_text_style\" align=\"right\" dir=\"rtl\">&#64831;&#1603;&#1614;&#1604;&#1575;&#1617;&#1614; &#1576;&#1614;&#1604;&#1618; &#1578;&#1615;&#1603;&#1614;&#1584;&#1617;&#1616;&#1576;&#1615;&#1608;&#1606;&#1614; &#1576;&#1616;&#1575;&#1604;&#1583;&#1617;&#1616;&#1610;&#1606;&#1616; &#64830;</div></p>\\n<p>(Nay! But you deny (the Day of) Ad-Din.) meaning, `you are only compelled to oppose the Most Generous and meet Him with disobedience, by your rejection in your hearts of the Hereafter, the recompense and the reckoning.' Concerning Allah's statement,</p>\\n<p dir=\"rtl\"><div class=\"arabic_text_style\" align=\"right\" dir=\"rtl\">&#64831;&#1608;&#1614;&#1573;&#1616;&#1606;&#1617;&#1614; &#1593;&#1614;&#1604;&#1614;&#1610;&#1618;&#1603;&#1615;&#1605;&#1618; &#1604;&#1614;&#1581;&#1614;&#1600;&#1601;&#1616;&#1592;&#1616;&#1610;&#1606;&#1614; - &#1603;&#1616;&#1585;&#1614;&#1575;&#1605;&#1575;&#1611; &#1603;&#1614;&#1600;&#1578;&#1616;&#1576;&#1616;&#1610;&#1606;&#1614; - &#1610;&#1614;&#1593;&#1618;&#1604;&#1614;&#1605;&#1615;&#1608;&#1606;&#1614; &#1605;&#1614;&#1575; &#1578;&#1614;&#1601;&#1618;&#1593;&#1614;&#1604;&#1615;&#1608;&#1606;&#1614; &#64830;</div></p>\\n<p>(But verily, over you to watch you (are) Kiraman Katibin, they know all that you do.) (82:10-12) meaning, `indeed there are noble guardian angels over you, so do not meet them with evil deeds, because they write down all that you do.'</p>\\n\\t\\t\\t</note>"
  },
  {
    "SurahNumber": "82",
    "AyahFrom": "13",
    "AyahTo": "19",
    "AyahText": " <p dir=\"rtl\"><div class=\"arabic_text_style\" align=\"right\" dir=\"rtl\">\\n&#1573;&#1616;&#1606;&#1617;&#1614; &#1575;&#1604;&#1575;&#1617;&#1612;&#1576;&#1618;&#1585;&#1614;&#1575;&#1585;&#1614; &#1604;&#1614;&#1601;&#1616;&#1609; &#1606;&#1614;&#1593;&#1616;&#1610;&#1605;&#1613; - &#1608;&#1614;&#1573;&#1616;&#1606;&#1617;&#1614; &#1575;&#1604;&#1618;&#1601;&#1615;&#1580;&#1617;&#1614;&#1575;&#1585;&#1614; &#1604;&#1614;&#1601;&#1616;&#1609; &#1580;&#1614;&#1581;&#1616;&#1610;&#1605;&#1613; - &#1610;&#1614;&#1589;&#1618;&#1604;&#1614;&#1608;&#1618;&#1606;&#1614;&#1607;&#1614;&#1575; &#1610;&#1614;&#1608;&#1618;&#1605;&#1614; &#1575;&#1604;&#1583;&#1617;&#1616;&#1610;&#1606;&#1616; - &#1608;&#1614;&#1605;&#1614;&#1575; &#1607;&#1615;&#1605;&#1614; &#1593;&#1614;&#1606;&#1618;&#1607;&#1614;&#1575; &#1576;&#1616;&#1594;&#1614;&#1570;&#1574;&#1616;&#1576;&#1616;&#1610;&#1606;&#1614; - &#1608;&#1614;&#1605;&#1614;&#1570; &#1571;&#1614;&#1583;&#1618;&#1585;&#1614;&#1575;&#1603;&#1614; &#1605;&#1614;&#1575; &#1610;&#1614;&#1608;&#1618;&#1605;&#1615; &#1575;&#1604;&#1583;&#1617;&#1616;&#1610;&#1606;&#1616; - &#1579;&#1615;&#1605;&#1617;&#1614; &#1605;&#1614;&#1570; &#1571;&#1614;&#1583;&#1618;&#1585;&#1614;&#1575;&#1603;&#1614; &#1605;&#1614;&#1575; &#1610;&#1614;&#1608;&#1618;&#1605;&#1615; &#1575;&#1604;&#1583;&#1617;&#1616;&#1610;&#1606;&#1616; - &#1610;&#1614;&#1608;&#1618;&#1605;&#1614; &#1604;&#1575;&#1614; &#1578;&#1614;&#1605;&#1618;&#1604;&#1616;&#1603;&#1615; &#1606;&#1614;&#1601;&#1618;&#1587;&#1612; &#1604;&#1616;&#1606;&#1614;&#1601;&#1618;&#1587;&#1613; &#1588;&#1614;&#1610;&#1618;&#1574;&#1575;&#1611; &#1608;&#1614;&#1575;&#1604;&#1575;&#1617;&#1612;&#1605;&#1618;&#1585;&#1615; &#1610;&#1614;&#1608;&#1618;&#1605;&#1614;&#1574;&#1616;&#1584;&#1613; &#1604;&#1616;&#1604;&#1617;&#1614;&#1607;&#1616; </div></p>\\n<i><p><b>13.</b> Verily, the Abrar (the righteous believers) will be in Delight; <b>14.</b> And verily, the wicked will be in the blazing Fire (Hell), <b>15.</b> Therein they will enter, and taste its burning flame on the Day of Recompense, <b>16.</b> And they will not be absent therefrom. <b>17.</b>And what will make you know what the Day of Recompense is <b>18.</b> Again, what will make you know what the Day of Recompense is <b>19.</b> (It will be) the Day when no person shall have power for another, and the Decision, that Day, will be with Allah.</p></i> \\n",
    "Text": "<note id=\"3\">\\n\\t\\t\\t\\t <div class=\"title\">The Reward of the Righteous &amp;the Sinners Allah informs of what the righteous will receive of delight</div>\\n<br> <p>They are those who obeyed Allah and did not meet Him with disobedience (sins). Then He mentions that the evildoers will be in Hell and eternal torment. Due to this He says,</p>\\n<p dir=\"rtl\"><div class=\"arabic_text_style\" align=\"right\" dir=\"rtl\">&#64831;&#1610;&#1614;&#1589;&#1618;&#1604;&#1614;&#1608;&#1618;&#1606;&#1614;&#1607;&#1614;&#1575; &#1610;&#1614;&#1608;&#1618;&#1605;&#1614; &#1575;&#1604;&#1583;&#1617;&#1616;&#1610;&#1606;&#1616; &#64830;</div></p>\\n<p>(Therein they will enter, and taste its burning flame on the Day of Recompense,) meaning, the Day of Reckoning, Recompense, and Judgement.</p>\\n<p dir=\"rtl\"><div class=\"arabic_text_style\" align=\"right\" dir=\"rtl\">&#64831;&#1608;&#1614;&#1605;&#1614;&#1575; &#1607;&#1615;&#1605;&#1614; &#1593;&#1614;&#1606;&#1618;&#1607;&#1614;&#1575; &#1576;&#1616;&#1594;&#1614;&#1570;&#1574;&#1616;&#1576;&#1616;&#1610;&#1606;&#1614; &#64830;</div></p>\\n<p>(And they will not be absent therefrom.) meaning, they will not be absent for even one hour from the torment. The torment will not be lightened from them, nor will they be granted the death that they will be requesting, or any rest -- not even for a single day. Allah then says,</p>\\n<p dir=\"rtl\"><div class=\"arabic_text_style\" align=\"right\" dir=\"rtl\">&#64831;&#1608;&#1614;&#1605;&#1614;&#1570; &#1571;&#1614;&#1583;&#1618;&#1585;&#1614;&#1575;&#1603;&#1614; &#1605;&#1614;&#1575; &#1610;&#1614;&#1608;&#1618;&#1605;&#1615; &#1575;&#1604;&#1583;&#1617;&#1616;&#1610;&#1606;&#1616; &#64830;</div></p>\\n<p>(And what will make you know what the Day of Recompense is) This is a magnification of the affair of the Day of Judgement. Then Allah affirms it by saying,</p>\\n<p dir=\"rtl\"><div class=\"arabic_text_style\" align=\"right\" dir=\"rtl\">&#64831;&#1579;&#1615;&#1605;&#1617;&#1614; &#1605;&#1614;&#1570; &#1571;&#1614;&#1583;&#1618;&#1585;&#1614;&#1575;&#1603;&#1614; &#1605;&#1614;&#1575; &#1610;&#1614;&#1608;&#1618;&#1605;&#1615; &#1575;&#1604;&#1583;&#1617;&#1616;&#1610;&#1606;&#1616; &#64830;</div></p>\\n<p>(Again, what will make you know what the Day of Recompense is) Then He explains this by saying,</p>\\n<p dir=\"rtl\"><div class=\"arabic_text_style\" align=\"right\" dir=\"rtl\">&#64831;&#1610;&#1614;&#1608;&#1618;&#1605;&#1614; &#1604;&#1575;&#1614; &#1578;&#1614;&#1605;&#1618;&#1604;&#1616;&#1603;&#1615; &#1606;&#1614;&#1601;&#1618;&#1587;&#1612; &#1604;&#1616;&#1606;&#1614;&#1601;&#1618;&#1587;&#1613; &#1588;&#1614;&#1610;&#1618;&#1574;&#1575;&#1611;&#64830;</div></p>\\n<p>((It will be) the Day when no person shall have power for another, ) meaning, no one will be able to benefit anyone else, or help him out of that which he will be in, unless Allah gives permission to whomever He wishes and is pleased with. We will mention here a Hadith (where the Prophet said),</p>\\n<p dir=\"rtl\"><div class=\"arabic_text_style\" align=\"right\" dir=\"rtl\">&laquo;&#1610;&#1614;&#1575; &#1576;&#1614;&#1606;&#1616;&#1610; &#1607;&#1614;&#1575;&#1588;&#1616;&#1605;&#1548; &#1571;&#1614;&#1606;&#1618;&#1602;&#1616;&#1584;&#1615;&#1608;&#1575; &#1571;&#1614;&#1606;&#1618;&#1601;&#1615;&#1587;&#1614;&#1603;&#1615;&#1605;&#1618; &#1605;&#1616;&#1606;&#1614; &#1575;&#1604;&#1606;&#1617;&#1614;&#1575;&#1585;&#1616; &#1604;&#1614;&#1575; &#1571;&#1614;&#1605;&#1618;&#1604;&#1616;&#1603;&#1615; &#1604;&#1614;&#1603;&#1615;&#1605;&#1618; &#1605;&#1616;&#1606;&#1614; &#1575;&#1604;&#1604;&#1607;&#1616; &#1588;&#1614;&#1610;&#1618;&#1574;&#1611;&#1575;&raquo;</div></p>\\n<p>(O children of Hashim! Save yourselves from the Fire, for I have no power to cause you any benefit from Allah.) This has been mentioned previously at the end of the Tafsir of Surat Ash-Shu`ara&#39; (see 26:214). Thus, Allah says,</p>\\n<p dir=\"rtl\"><div class=\"arabic_text_style\" align=\"right\" dir=\"rtl\">&#64831;&#1608;&#1614;&#1575;&#1604;&#1575;&#1617;&#1612;&#1605;&#1618;&#1585;&#1615; &#1610;&#1614;&#1608;&#1618;&#1605;&#1614;&#1574;&#1616;&#1584;&#1613; &#1604;&#1616;&#1604;&#1617;&#1614;&#1607;&#1616;&#64830;</div></p>\\n<p>(and the Decision, that Day, will be with Allah.) &quot;By Allah, the Decision is for Allah today (now), but on that Day no one will try to dispute with Him about it.&#39;&#39; This is the end of the Tafsir of Surat Al-Infitar. All praise and blessings are due to Allah, and He is the Giver of success and freedom from error.</p> \\n\\t\\t\\t</note>"
  }
]
