[
    {
        "BookCode":  "TLT",
        "SurahNumber":  "9",
        "AyahNumber":  "1",
        "Recitation":  "Alafasy_128kbps/009001",
        "Body":  "Bar\u003cu\u003ea\u003c/u\u003eatun mina All\u003cu\u003ea\u003c/u\u003ehi warasoolihi il\u003cu\u003ea\u003c/u\u003e alla\u003cu\u003eth\u003c/u\u003eeena AA\u003cu\u003ea\u003c/u\u003ehadtum mina almushrikeen\u003cb\u003ea\u003c/b\u003e"
    },
    {
        "BookCode":  "TLT",
        "SurahNumber":  "9",
        "AyahNumber":  "10",
        "Recitation":  "Alafasy_128kbps/009010",
        "Body":  "L\u003cu\u003ea\u003c/u\u003e yarquboona fee muminin illan wal\u003cu\u003ea\u003c/u\u003e \u003cu\u003eth\u003c/u\u003eimmatan waol\u003cu\u003ea\u003c/u\u003eika humu almuAAtadoon\u003cb\u003ea\u003c/b\u003e"
    },
    {
        "BookCode":  "TLT",
        "SurahNumber":  "9",
        "AyahNumber":  "100",
        "Recitation":  "Alafasy_128kbps/009100",
        "Body":  "Wa\u003cb\u003eal\u003c/b\u003ess\u003cu\u003ea\u003c/u\u003ebiqoona alawwaloona mina almuh\u003cu\u003ea\u003c/u\u003ejireena wa\u003cb\u003ea\u003c/b\u003elan\u003cu\u003esa\u003c/u\u003eri wa\u003cb\u003ea\u003c/b\u003ella\u003cu\u003eth\u003c/u\u003eeena ittabaAAoohum bii\u003cu\u003eh\u003c/u\u003es\u003cu\u003ea\u003c/u\u003enin ra\u003cu\u003ed\u003c/u\u003eiya All\u003cu\u003ea\u003c/u\u003ehu AAanhum wara\u003cu\u003ed\u003c/u\u003eoo AAanhu waaAAadda lahum jann\u003cu\u003ea\u003c/u\u003etin tajree ta\u003cu\u003eh\u003c/u\u003etah\u003cu\u003ea\u003c/u\u003e alanh\u003cu\u003ea\u003c/u\u003eru kh\u003cu\u003ea\u003c/u\u003elideena feeh\u003cu\u003ea\u003c/u\u003e abadan \u003cu\u003etha\u003c/u\u003elika alfawzu alAAa\u003ci\u003e\u003cu\u003eth\u003c/u\u003e\u003c/i\u003eeem\u003cb\u003eu\u003c/b\u003e"
    },
    {
        "BookCode":  "TLT",
        "SurahNumber":  "9",
        "AyahNumber":  "101",
        "Recitation":  "Alafasy_128kbps/009101",
        "Body":  "Wamimman \u003cu\u003eh\u003c/u\u003eawlakum mina alaAAr\u003cu\u003ea\u003c/u\u003ebi mun\u003cu\u003ea\u003c/u\u003efiqoona wamin ahli almadeenati maradoo AAal\u003cu\u003ea\u003c/u\u003e a\u003cb\u003el\u003c/b\u003ennif\u003cu\u003ea\u003c/u\u003eqi l\u003cu\u003ea\u003c/u\u003e taAAlamuhum na\u003cu\u003eh\u003c/u\u003enu naAAlamuhum sanuAAa\u003cu\u003ethth\u003c/u\u003eibuhum marratayni thumma yuraddoona il\u003cu\u003ea\u003c/u\u003e AAa\u003cu\u003etha\u003c/u\u003ebin AAa\u003ci\u003e\u003cu\u003eth\u003c/u\u003e\u003c/i\u003eeem\u003cb\u003ein\u003c/b\u003e"
    },
    {
        "BookCode":  "TLT",
        "SurahNumber":  "9",
        "AyahNumber":  "102",
        "Recitation":  "Alafasy_128kbps/009102",
        "Body":  "Wa\u003cu\u003ea\u003c/u\u003ekharoona iAAtarafoo bi\u003cu\u003eth\u003c/u\u003eunoobihim khala\u003cu\u003et\u003c/u\u003eoo AAamalan \u003cu\u003esa\u003c/u\u003eli\u003cu\u003eh\u003c/u\u003ean wa\u003cu\u003ea\u003c/u\u003ekhara sayyian AAas\u003cu\u003ea\u003c/u\u003e All\u003cu\u003ea\u003c/u\u003ehu an yatooba AAalayhim inna All\u003cu\u003ea\u003c/u\u003eha ghafoorun ra\u003cu\u003eh\u003c/u\u003eeem\u003cb\u003eun\u003c/b\u003e"
    },
    {
        "BookCode":  "TLT",
        "SurahNumber":  "9",
        "AyahNumber":  "103",
        "Recitation":  "Alafasy_128kbps/009103",
        "Body":  "Khu\u003cu\u003eth\u003c/u\u003e min amw\u003cu\u003ea\u003c/u\u003elihim \u003cu\u003es\u003c/u\u003eadaqatan tu\u003cu\u003et\u003c/u\u003eahhiruhum watuzakkeehim bih\u003cu\u003ea\u003c/u\u003e wa\u003cu\u003es\u003c/u\u003ealli AAalayhim inna \u003cu\u003es\u003c/u\u003eal\u003cu\u003ea\u003c/u\u003etaka sakanun lahum wa\u003cb\u003eA\u003c/b\u003ell\u003cu\u003ea\u003c/u\u003ehu sameeAAun AAaleem\u003cb\u003eun\u003c/b\u003e"
    },
    {
        "BookCode":  "TLT",
        "SurahNumber":  "9",
        "AyahNumber":  "104",
        "Recitation":  "Alafasy_128kbps/009104",
        "Body":  "Alam yaAAlamoo anna All\u003cu\u003ea\u003c/u\u003eha huwa yaqbalu a\u003cb\u003el\u003c/b\u003ettawbata AAan AAib\u003cu\u003ea\u003c/u\u003edihi wayakhu\u003cu\u003eth\u003c/u\u003eu a\u003cb\u003el\u003c/b\u003e\u003cu\u003ess\u003c/u\u003eadaq\u003cu\u003ea\u003c/u\u003eti waanna All\u003cu\u003ea\u003c/u\u003eha huwa a\u003cb\u003el\u003c/b\u003ettaww\u003cu\u003ea\u003c/u\u003ebu a\u003cb\u003el\u003c/b\u003erra\u003cu\u003eh\u003c/u\u003eeem\u003cb\u003eu\u003c/b\u003e"
    },
    {
        "BookCode":  "TLT",
        "SurahNumber":  "9",
        "AyahNumber":  "105",
        "Recitation":  "Alafasy_128kbps/009105",
        "Body":  "Waquli iAAmaloo fasayar\u003cu\u003ea\u003c/u\u003e All\u003cu\u003ea\u003c/u\u003ehu AAamalakum warasooluhu wa\u003cb\u003ea\u003c/b\u003elmuminoona wasaturaddoona il\u003cu\u003ea\u003c/u\u003e AA\u003cu\u003ea\u003c/u\u003elimi alghaybi wa\u003cb\u003eal\u003c/b\u003eshshah\u003cu\u003ea\u003c/u\u003edati fayunabbiokum bim\u003cu\u003ea\u003c/u\u003e kuntum taAAmaloon\u003cb\u003ea\u003c/b\u003e"
    },
    {
        "BookCode":  "TLT",
        "SurahNumber":  "9",
        "AyahNumber":  "106",
        "Recitation":  "Alafasy_128kbps/009106",
        "Body":  "Wa\u003cu\u003ea\u003c/u\u003ekharoona murjawna liamri All\u003cu\u003ea\u003c/u\u003ehi imm\u003cu\u003ea\u003c/u\u003e yuAAa\u003cu\u003ethth\u003c/u\u003eibuhum waimm\u003cu\u003ea\u003c/u\u003e yatoobu AAalayhim wa\u003cb\u003eA\u003c/b\u003ell\u003cu\u003ea\u003c/u\u003ehu AAaleemun \u003cu\u003eh\u003c/u\u003eakeem\u003cb\u003eun\u003c/b\u003e"
    },
    {
        "BookCode":  "TLT",
        "SurahNumber":  "9",
        "AyahNumber":  "107",
        "Recitation":  "Alafasy_128kbps/009107",
        "Body":  "Wa\u003cb\u003ea\u003c/b\u003ella\u003cu\u003eth\u003c/u\u003eeena ittakha\u003cu\u003eth\u003c/u\u003eoo masjidan \u003cu\u003ed\u003c/u\u003eir\u003cu\u003ea\u003c/u\u003eran wakufran watafreeqan bayna almumineena wair\u003cu\u003esa\u003c/u\u003edan liman \u003cu\u003eha\u003c/u\u003eraba All\u003cu\u003ea\u003c/u\u003eha warasoolahu min qablu walaya\u003cu\u003eh\u003c/u\u003elifunna in aradn\u003cu\u003ea\u003c/u\u003e ill\u003cu\u003ea\u003c/u\u003e al\u003cu\u003eh\u003c/u\u003eusn\u003cu\u003ea\u003c/u\u003e wa\u003cb\u003eA\u003c/b\u003ell\u003cu\u003ea\u003c/u\u003ehu yashhadu innahum lak\u003cu\u003eath\u003c/u\u003eiboon\u003cb\u003ea\u003c/b\u003e"
    },
    {
        "BookCode":  "TLT",
        "SurahNumber":  "9",
        "AyahNumber":  "108",
        "Recitation":  "Alafasy_128kbps/009108",
        "Body":  "L\u003cu\u003ea\u003c/u\u003e taqum feehi abadan lamasjidun ossisa AAal\u003cu\u003ea\u003c/u\u003e a\u003cb\u003el\u003c/b\u003ettaqw\u003cu\u003ea\u003c/u\u003e min awwali yawmin a\u003cu\u003eh\u003c/u\u003eaqqu an taqooma feehi feehi rij\u003cu\u003ea\u003c/u\u003elun yu\u003cu\u003eh\u003c/u\u003eibboona an yata\u003cu\u003et\u003c/u\u003eahharoo wa\u003cb\u003eA\u003c/b\u003ell\u003cu\u003ea\u003c/u\u003ehu yu\u003cu\u003eh\u003c/u\u003eibbu almu\u003cu\u003ett\u003c/u\u003eahhireen\u003cb\u003ea\u003c/b\u003e"
    },
    {
        "BookCode":  "TLT",
        "SurahNumber":  "9",
        "AyahNumber":  "109",
        "Recitation":  "Alafasy_128kbps/009109",
        "Body":  "Afaman assasa buny\u003cu\u003ea\u003c/u\u003enahu AAal\u003cu\u003ea\u003c/u\u003e taqw\u003cu\u003ea\u003c/u\u003e mina All\u003cu\u003ea\u003c/u\u003ehi wari\u003cu\u003ed\u003c/u\u003ew\u003cu\u003ea\u003c/u\u003enin khayrun am man assasa buny\u003cu\u003ea\u003c/u\u003enahu AAal\u003cu\u003ea\u003c/u\u003e shaf\u003cu\u003ea\u003c/u\u003e jurufin h\u003cu\u003ea\u003c/u\u003erin fa\u003cb\u003ei\u003c/b\u003enh\u003cu\u003ea\u003c/u\u003era bihi fee n\u003cu\u003ea\u003c/u\u003eri jahannama wa\u003cb\u003eA\u003c/b\u003ell\u003cu\u003ea\u003c/u\u003ehu l\u003cu\u003ea\u003c/u\u003e yahdee alqawma a\u003cb\u003el\u003c/b\u003e\u003ci\u003e\u003cu\u003ethth\u003c/u\u003e\u003c/i\u003e\u003cu\u003ea\u003c/u\u003elimeen\u003cb\u003ea\u003c/b\u003e"
    },
    {
        "BookCode":  "TLT",
        "SurahNumber":  "9",
        "AyahNumber":  "11",
        "Recitation":  "Alafasy_128kbps/009011",
        "Body":  "Fain t\u003cu\u003ea\u003c/u\u003eboo waaq\u003cu\u003ea\u003c/u\u003emoo a\u003cb\u003el\u003c/b\u003e\u003cu\u003ess\u003c/u\u003eal\u003cu\u003ea\u003c/u\u003eta wa\u003cu\u003ea\u003c/u\u003etawoo a\u003cb\u003el\u003c/b\u003ezzak\u003cu\u003ea\u003c/u\u003eta faikhw\u003cu\u003ea\u003c/u\u003enukum fee a\u003cb\u003el\u003c/b\u003eddeeni wanufa\u003cu\u003ess\u003c/u\u003eilu al\u003cu\u003ea\u003c/u\u003ey\u003cu\u003ea\u003c/u\u003eti liqawmin yaAAlamoon\u003cb\u003ea\u003c/b\u003e"
    },
    {
        "BookCode":  "TLT",
        "SurahNumber":  "9",
        "AyahNumber":  "110",
        "Recitation":  "Alafasy_128kbps/009110",
        "Body":  "L\u003cu\u003ea\u003c/u\u003e yaz\u003cu\u003ea\u003c/u\u003elu buny\u003cu\u003ea\u003c/u\u003enuhumu alla\u003cu\u003eth\u003c/u\u003eee banaw reebatan fee quloobihim ill\u003cu\u003ea\u003c/u\u003e an taqa\u003cu\u003ett\u003c/u\u003eaAAa quloobuhum wa\u003cb\u003eA\u003c/b\u003ell\u003cu\u003ea\u003c/u\u003ehu AAaleemun \u003cu\u003eh\u003c/u\u003eakeem\u003cb\u003eun\u003c/b\u003e"
    },
    {
        "BookCode":  "TLT",
        "SurahNumber":  "9",
        "AyahNumber":  "111",
        "Recitation":  "Alafasy_128kbps/009111",
        "Body":  "Inna All\u003cu\u003ea\u003c/u\u003eha ishtar\u003cu\u003ea\u003c/u\u003e mina almumineena anfusahum waamw\u003cu\u003ea\u003c/u\u003elahum bianna lahumu aljannata yuq\u003cu\u003ea\u003c/u\u003etiloona fee sabeeli All\u003cu\u003ea\u003c/u\u003ehi fayaqtuloona wayuqtaloona waAAdan AAalayhi \u003cu\u003eh\u003c/u\u003eaqqan fee a\u003cb\u003el\u003c/b\u003ettawr\u003cu\u003ea\u003c/u\u003eti wa\u003cb\u003ea\u003c/b\u003elinjeeli wa\u003cb\u003ea\u003c/b\u003elqur\u003cu\u003ea\u003c/u\u003eni waman awf\u003cu\u003ea\u003c/u\u003e biAAahdihi mina All\u003cu\u003ea\u003c/u\u003ehi fa\u003cb\u003ei\u003c/b\u003estabshiroo bibayAAikumu alla\u003cu\u003eth\u003c/u\u003eee b\u003cu\u003ea\u003c/u\u003eyaAAtum bihi wa\u003cu\u003etha\u003c/u\u003elika huwa alfawzu alAAa\u003ci\u003e\u003cu\u003eth\u003c/u\u003e\u003c/i\u003eeem\u003cb\u003eu\u003c/b\u003e"
    },
    {
        "BookCode":  "TLT",
        "SurahNumber":  "9",
        "AyahNumber":  "112",
        "Recitation":  "Alafasy_128kbps/009112",
        "Body":  "A\u003cb\u003el\u003c/b\u003ett\u003cu\u003ea\u003c/u\u003eiboona alAA\u003cu\u003ea\u003c/u\u003ebidoona al\u003cu\u003eha\u003c/u\u003emidoona a\u003cb\u003el\u003c/b\u003ess\u003cu\u003ea\u003c/u\u003ei\u003cu\u003eh\u003c/u\u003eoona a\u003cb\u003el\u003c/b\u003err\u003cu\u003ea\u003c/u\u003ekiAAoona a\u003cb\u003el\u003c/b\u003ess\u003cu\u003ea\u003c/u\u003ejidoona al\u003cu\u003ea\u003c/u\u003emiroona bi\u003cb\u003ea\u003c/b\u003elmaAAroofi wa\u003cb\u003eal\u003c/b\u003enn\u003cu\u003ea\u003c/u\u003ehoona AAani almunkari wa\u003cb\u003ea\u003c/b\u003el\u003cu\u003eha\u003c/u\u003efi\u003ci\u003e\u003cu\u003eth\u003c/u\u003e\u003c/i\u003eoona li\u003cu\u003eh\u003c/u\u003eudoodi All\u003cu\u003ea\u003c/u\u003ehi wabashshiri almumineen\u003cb\u003ea\u003c/b\u003e"
    },
    {
        "BookCode":  "TLT",
        "SurahNumber":  "9",
        "AyahNumber":  "113",
        "Recitation":  "Alafasy_128kbps/009113",
        "Body":  "M\u003cu\u003ea\u003c/u\u003e k\u003cu\u003ea\u003c/u\u003ena li\u003cb\u003el\u003c/b\u003ennabiyyi wa\u003cb\u003ea\u003c/b\u003ella\u003cu\u003eth\u003c/u\u003eeena \u003cu\u003ea\u003c/u\u003emanoo an yastaghfiroo lilmushrikeena walaw k\u003cu\u003ea\u003c/u\u003enoo olee qurb\u003cu\u003ea\u003c/u\u003e min baAAdi m\u003cu\u003ea\u003c/u\u003e tabayyana lahum annahum a\u003cu\u003es\u003c/u\u003e\u003cu\u003eha\u003c/u\u003ebu alja\u003cu\u003eh\u003c/u\u003eeem\u003cb\u003ei\u003c/b\u003e"
    },
    {
        "BookCode":  "TLT",
        "SurahNumber":  "9",
        "AyahNumber":  "114",
        "Recitation":  "Alafasy_128kbps/009114",
        "Body":  "Wam\u003cu\u003ea\u003c/u\u003e k\u003cu\u003ea\u003c/u\u003ena istighf\u003cu\u003ea\u003c/u\u003eru ibr\u003cu\u003ea\u003c/u\u003eheema liabeehi ill\u003cu\u003ea\u003c/u\u003e AAan mawAAidatin waAAadah\u003cu\u003ea\u003c/u\u003e iyy\u003cu\u003ea\u003c/u\u003ehu falamm\u003cu\u003ea\u003c/u\u003e tabayyana lahu annahu AAaduwwun lill\u003cu\u003ea\u003c/u\u003ehi tabarraa minhu inna ibr\u003cu\u003ea\u003c/u\u003eheema laaww\u003cu\u003ea\u003c/u\u003ehun \u003cu\u003eh\u003c/u\u003ealeem\u003cb\u003eun\u003c/b\u003e"
    },
    {
        "BookCode":  "TLT",
        "SurahNumber":  "9",
        "AyahNumber":  "115",
        "Recitation":  "Alafasy_128kbps/009115",
        "Body":  "Wam\u003cu\u003ea\u003c/u\u003e k\u003cu\u003ea\u003c/u\u003ena All\u003cu\u003ea\u003c/u\u003ehu liyu\u003cu\u003ed\u003c/u\u003eilla qawman baAAda i\u003cu\u003eth\u003c/u\u003e had\u003cu\u003ea\u003c/u\u003ehum \u003cu\u003eh\u003c/u\u003eatt\u003cu\u003ea\u003c/u\u003e yubayyina lahum m\u003cu\u003ea\u003c/u\u003e yattaqoona inna All\u003cu\u003ea\u003c/u\u003eha bikulli shayin AAaleem\u003cb\u003eun\u003c/b\u003e"
    },
    {
        "BookCode":  "TLT",
        "SurahNumber":  "9",
        "AyahNumber":  "116",
        "Recitation":  "Alafasy_128kbps/009116",
        "Body":  "Inna All\u003cu\u003ea\u003c/u\u003eha lahu mulku a\u003cb\u003el\u003c/b\u003essam\u003cu\u003ea\u003c/u\u003ew\u003cu\u003ea\u003c/u\u003eti wa\u003cb\u003ea\u003c/b\u003elar\u003cu\u003ed\u003c/u\u003ei yu\u003cu\u003eh\u003c/u\u003eyee wayumeetu wam\u003cu\u003ea\u003c/u\u003e lakum min dooni All\u003cu\u003ea\u003c/u\u003ehi min waliyyin wal\u003cu\u003ea\u003c/u\u003e na\u003cu\u003es\u003c/u\u003eeer\u003cb\u003ein\u003c/b\u003e"
    },
    {
        "BookCode":  "TLT",
        "SurahNumber":  "9",
        "AyahNumber":  "117",
        "Recitation":  "Alafasy_128kbps/009117",
        "Body":  "Laqad t\u003cu\u003ea\u003c/u\u003eba All\u003cu\u003ea\u003c/u\u003ehu AAal\u003cu\u003ea\u003c/u\u003e a\u003cb\u003el\u003c/b\u003ennabiyyi wa\u003cb\u003ea\u003c/b\u003elmuh\u003cu\u003ea\u003c/u\u003ejireena wa\u003cb\u003ea\u003c/b\u003elan\u003cu\u003esa\u003c/u\u003eri alla\u003cu\u003eth\u003c/u\u003eeena ittabaAAoohu fee s\u003cu\u003ea\u003c/u\u003eAAati alAAusrati min baAAdi m\u003cu\u003ea\u003c/u\u003e k\u003cu\u003ea\u003c/u\u003eda yazeeghu quloobu fareeqin minhum thumma t\u003cu\u003ea\u003c/u\u003eba AAalayhim innahu bihim raoofun ra\u003cu\u003eh\u003c/u\u003eeem\u003cb\u003eun\u003c/b\u003e"
    },
    {
        "BookCode":  "TLT",
        "SurahNumber":  "9",
        "AyahNumber":  "118",
        "Recitation":  "Alafasy_128kbps/009118",
        "Body":  "WaAAal\u003cu\u003ea\u003c/u\u003e a\u003cb\u003el\u003c/b\u003eththal\u003cu\u003ea\u003c/u\u003ethati alla\u003cu\u003eth\u003c/u\u003eeena khullifoo \u003cu\u003eh\u003c/u\u003eatt\u003cu\u003ea\u003c/u\u003e i\u003cu\u003etha\u003c/u\u003e \u003cu\u003eda\u003c/u\u003eqat AAalayhimu alar\u003cu\u003ed\u003c/u\u003eu bim\u003cu\u003ea\u003c/u\u003e ra\u003cu\u003eh\u003c/u\u003eubat wa\u003cu\u003eda\u003c/u\u003eqat AAalayhim anfusuhum wa\u003ci\u003e\u003cu\u003eth\u003c/u\u003e\u003c/i\u003eannoo an l\u003cu\u003ea\u003c/u\u003e maljaa mina All\u003cu\u003ea\u003c/u\u003ehi ill\u003cu\u003ea\u003c/u\u003e ilayhi thumma t\u003cu\u003ea\u003c/u\u003eba AAalayhim liyatooboo inna All\u003cu\u003ea\u003c/u\u003eha huwa a\u003cb\u003el\u003c/b\u003ettaww\u003cu\u003ea\u003c/u\u003ebu a\u003cb\u003el\u003c/b\u003erra\u003cu\u003eh\u003c/u\u003eeem\u003cb\u003eu\u003c/b\u003e"
    },
    {
        "BookCode":  "TLT",
        "SurahNumber":  "9",
        "AyahNumber":  "119",
        "Recitation":  "Alafasy_128kbps/009119",
        "Body":  "Y\u003cu\u003ea\u003c/u\u003e ayyuh\u003cu\u003ea\u003c/u\u003e alla\u003cu\u003eth\u003c/u\u003eeena \u003cu\u003ea\u003c/u\u003emanoo ittaqoo All\u003cu\u003ea\u003c/u\u003eha wakoonoo maAAa a\u003cb\u003el\u003c/b\u003e\u003cu\u003essa\u003c/u\u003ediqeen\u003cb\u003ea\u003c/b\u003e"
    },
    {
        "BookCode":  "TLT",
        "SurahNumber":  "9",
        "AyahNumber":  "12",
        "Recitation":  "Alafasy_128kbps/009012",
        "Body":  "Wain nakathoo aym\u003cu\u003ea\u003c/u\u003enahum min baAAdi AAahdihim wa\u003cu\u003et\u003c/u\u003eaAAanoo fee deenikum faq\u003cu\u003ea\u003c/u\u003etiloo aimmata alkufri innahum l\u003cu\u003ea\u003c/u\u003e aym\u003cu\u003ea\u003c/u\u003ena lahum laAAallahum yantahoon\u003cb\u003ea\u003c/b\u003e"
    },
    {
        "BookCode":  "TLT",
        "SurahNumber":  "9",
        "AyahNumber":  "120",
        "Recitation":  "Alafasy_128kbps/009120",
        "Body":  "M\u003cu\u003ea\u003c/u\u003e k\u003cu\u003ea\u003c/u\u003ena liahli almadeenati waman \u003cu\u003eh\u003c/u\u003eawlahum mina alaAAr\u003cu\u003ea\u003c/u\u003ebi an yatakhallafoo AAan rasooli All\u003cu\u003ea\u003c/u\u003ehi wal\u003cu\u003ea\u003c/u\u003e yarghaboo bianfusihim AAan nafsihi \u003cu\u003etha\u003c/u\u003elika biannahum l\u003cu\u003ea\u003c/u\u003e yu\u003cu\u003es\u003c/u\u003eeebuhum \u003ci\u003e\u003cu\u003eth\u003c/u\u003e\u003c/i\u003eamaon wal\u003cu\u003ea\u003c/u\u003e na\u003cu\u003es\u003c/u\u003eabun wal\u003cu\u003ea\u003c/u\u003e makhma\u003cu\u003es\u003c/u\u003eatun fee sabeeli All\u003cu\u003ea\u003c/u\u003ehi wal\u003cu\u003ea\u003c/u\u003e ya\u003cu\u003et\u003c/u\u003eaoona maw\u003cu\u003et\u003c/u\u003eian yaghee\u003ci\u003e\u003cu\u003eth\u003c/u\u003e\u003c/i\u003eu alkuff\u003cu\u003ea\u003c/u\u003era wal\u003cu\u003ea\u003c/u\u003e yan\u003cu\u003ea\u003c/u\u003eloona min AAaduwwin naylan ill\u003cu\u003ea\u003c/u\u003e kutiba lahum bihi AAamalun \u003cu\u003esa\u003c/u\u003eli\u003cu\u003eh\u003c/u\u003eun inna All\u003cu\u003ea\u003c/u\u003eha l\u003cu\u003ea\u003c/u\u003e yu\u003cu\u003ed\u003c/u\u003eeeAAu ajra almu\u003cu\u003eh\u003c/u\u003esineen\u003cb\u003ea\u003c/b\u003e"
    },
    {
        "BookCode":  "TLT",
        "SurahNumber":  "9",
        "AyahNumber":  "121",
        "Recitation":  "Alafasy_128kbps/009121",
        "Body":  "Wal\u003cu\u003ea\u003c/u\u003e yunfiqoona nafaqatan \u003cu\u003es\u003c/u\u003eagheeratan wal\u003cu\u003ea\u003c/u\u003e kabeeratan wal\u003cu\u003ea\u003c/u\u003e yaq\u003cu\u003et\u003c/u\u003eaAAoona w\u003cu\u003ea\u003c/u\u003ediyan ill\u003cu\u003ea\u003c/u\u003e kutiba lahum liyajziyahumu All\u003cu\u003ea\u003c/u\u003ehu a\u003cu\u003eh\u003c/u\u003esana m\u003cu\u003ea\u003c/u\u003e k\u003cu\u003ea\u003c/u\u003enoo yaAAmaloon\u003cb\u003ea\u003c/b\u003e"
    },
    {
        "BookCode":  "TLT",
        "SurahNumber":  "9",
        "AyahNumber":  "122",
        "Recitation":  "Alafasy_128kbps/009122",
        "Body":  "Wam\u003cu\u003ea\u003c/u\u003e k\u003cu\u003ea\u003c/u\u003ena almuminoona liyanfiroo k\u003cu\u003ea\u003c/u\u003effatan falawl\u003cu\u003ea\u003c/u\u003e nafara min kulli firqatin minhum \u003cu\u003eta\u003c/u\u003eifatun liyatafaqqahoo fee a\u003cb\u003el\u003c/b\u003eddeeni waliyun\u003cu\u003eth\u003c/u\u003eiroo qawmahum i\u003cu\u003etha\u003c/u\u003e rajaAAoo ilayhim laAAallahum ya\u003cu\u003ehth\u003c/u\u003earoon\u003cb\u003ea\u003c/b\u003e"
    },
    {
        "BookCode":  "TLT",
        "SurahNumber":  "9",
        "AyahNumber":  "123",
        "Recitation":  "Alafasy_128kbps/009123",
        "Body":  "Y\u003cu\u003ea\u003c/u\u003e ayyuh\u003cu\u003ea\u003c/u\u003e alla\u003cu\u003eth\u003c/u\u003eeena \u003cu\u003ea\u003c/u\u003emanoo q\u003cu\u003ea\u003c/u\u003etiloo alla\u003cu\u003eth\u003c/u\u003eeena yaloonakum mina alkuff\u003cu\u003ea\u003c/u\u003eri walyajidoo feekum ghil\u003ci\u003e\u003cu\u003eth\u003c/u\u003e\u003c/i\u003eatan wa\u003cb\u003ei\u003c/b\u003eAAlamoo anna All\u003cu\u003ea\u003c/u\u003eha maAAa almuttaqeen\u003cb\u003ea\u003c/b\u003e"
    },
    {
        "BookCode":  "TLT",
        "SurahNumber":  "9",
        "AyahNumber":  "124",
        "Recitation":  "Alafasy_128kbps/009124",
        "Body":  "Wai\u003cu\u003etha\u003c/u\u003e m\u003cu\u003ea\u003c/u\u003e onzilat sooratun faminhum man yaqoolu ayyukum z\u003cu\u003ea\u003c/u\u003edathu h\u003cu\u003eath\u003c/u\u003eihi eem\u003cu\u003ea\u003c/u\u003enan faamm\u003cu\u003ea\u003c/u\u003e alla\u003cu\u003eth\u003c/u\u003eeena \u003cu\u003ea\u003c/u\u003emanoo faz\u003cu\u003ea\u003c/u\u003edathum eem\u003cu\u003ea\u003c/u\u003enan wahum yastabshiroon\u003cb\u003ea\u003c/b\u003e"
    },
    {
        "BookCode":  "TLT",
        "SurahNumber":  "9",
        "AyahNumber":  "125",
        "Recitation":  "Alafasy_128kbps/009125",
        "Body":  "Waamm\u003cu\u003ea\u003c/u\u003e alla\u003cu\u003eth\u003c/u\u003eeena fee quloobihim mara\u003cu\u003ed\u003c/u\u003eun faz\u003cu\u003ea\u003c/u\u003edathum rijsan il\u003cu\u003ea\u003c/u\u003e rijsihim wam\u003cu\u003ea\u003c/u\u003etoo wahum k\u003cu\u003ea\u003c/u\u003efiroon\u003cb\u003ea\u003c/b\u003e"
    },
    {
        "BookCode":  "TLT",
        "SurahNumber":  "9",
        "AyahNumber":  "126",
        "Recitation":  "Alafasy_128kbps/009126",
        "Body":  "Awal\u003cu\u003ea\u003c/u\u003e yarawna annahum yuftanoona fee kulli AA\u003cu\u003ea\u003c/u\u003emin marratan aw marratayni thumma l\u003cu\u003ea\u003c/u\u003e yatooboona wal\u003cu\u003ea\u003c/u\u003e hum ya\u003cu\u003ethth\u003c/u\u003eakkaroon\u003cb\u003ea\u003c/b\u003e"
    },
    {
        "BookCode":  "TLT",
        "SurahNumber":  "9",
        "AyahNumber":  "127",
        "Recitation":  "Alafasy_128kbps/009127",
        "Body":  "Wai\u003cu\u003etha\u003c/u\u003e m\u003cu\u003ea\u003c/u\u003e onzilat sooratun na\u003ci\u003e\u003cu\u003eth\u003c/u\u003e\u003c/i\u003eara baAA\u003cu\u003ed\u003c/u\u003euhum il\u003cu\u003ea\u003c/u\u003e baAA\u003cu\u003ed\u003c/u\u003ein hal yar\u003cu\u003ea\u003c/u\u003ekum min a\u003cu\u003eh\u003c/u\u003eadin thumma in\u003cu\u003es\u003c/u\u003earafoo \u003cu\u003es\u003c/u\u003earafa All\u003cu\u003ea\u003c/u\u003ehu quloobahum biannahum qawmun l\u003cu\u003ea\u003c/u\u003e yafqahoon\u003cb\u003ea\u003c/b\u003e"
    },
    {
        "BookCode":  "TLT",
        "SurahNumber":  "9",
        "AyahNumber":  "128",
        "Recitation":  "Alafasy_128kbps/009128",
        "Body":  "Laqad j\u003cu\u003ea\u003c/u\u003eakum rasoolun min anfusikum AAazeezun AAalayhi m\u003cu\u003ea \u003c/u\u003eAAanittum \u003cu\u003eh\u003c/u\u003earee\u003cu\u003es\u003c/u\u003eun AAalaykum bi\u003cb\u003ea\u003c/b\u003elmumineena raoofun ra\u003cu\u003eh\u003c/u\u003eeem\u003cb\u003eun\u003c/b\u003e"
    },
    {
        "BookCode":  "TLT",
        "SurahNumber":  "9",
        "AyahNumber":  "129",
        "Recitation":  "Alafasy_128kbps/009129",
        "Body":  "Fain tawallaw faqul \u003cu\u003eh\u003c/u\u003easbiya All\u003cu\u003ea\u003c/u\u003ehu l\u003cu\u003ea\u003c/u\u003e il\u003cu\u003ea\u003c/u\u003eha ill\u003cu\u003ea\u003c/u\u003e huwa AAalayhi tawakkaltu wahuwa rabbu alAAarshi alAAa\u003ci\u003e\u003cu\u003eth\u003c/u\u003e\u003c/i\u003eeem\u003cb\u003ei\u003c/b\u003e"
    },
    {
        "BookCode":  "TLT",
        "SurahNumber":  "9",
        "AyahNumber":  "13",
        "Recitation":  "Alafasy_128kbps/009013",
        "Body":  "Al\u003cu\u003ea\u003c/u\u003e tuq\u003cu\u003ea\u003c/u\u003etiloona qawman nakathoo aym\u003cu\u003ea\u003c/u\u003enahum wahammoo biikhr\u003cu\u003ea\u003c/u\u003eji a\u003cb\u003el\u003c/b\u003errasooli wahum badaookum awwala marratin atakhshawnahum fa\u003cb\u003eA\u003c/b\u003ell\u003cu\u003ea\u003c/u\u003ehu a\u003cu\u003eh\u003c/u\u003eaqqu an takhshawhu in kuntum mumineen\u003cb\u003ea\u003c/b\u003e"
    },
    {
        "BookCode":  "TLT",
        "SurahNumber":  "9",
        "AyahNumber":  "14",
        "Recitation":  "Alafasy_128kbps/009014",
        "Body":  "Q\u003cu\u003ea\u003c/u\u003etiloohum yuAAa\u003cu\u003ethth\u003c/u\u003eibhumu All\u003cu\u003ea\u003c/u\u003ehu biaydeekum wayukhzihim wayan\u003cu\u003es\u003c/u\u003eurkum AAalayhim wayashfi \u003cu\u003es\u003c/u\u003eudoora qawmin mumineen\u003cb\u003ea\u003c/b\u003e"
    },
    {
        "BookCode":  "TLT",
        "SurahNumber":  "9",
        "AyahNumber":  "15",
        "Recitation":  "Alafasy_128kbps/009015",
        "Body":  "Wayu\u003cu\u003eth\u003c/u\u003ehib ghay\u003ci\u003e\u003cu\u003eth\u003c/u\u003e\u003c/i\u003ea quloobihim wayatoobu All\u003cu\u003ea\u003c/u\u003ehu AAal\u003cu\u003ea\u003c/u\u003e man yash\u003cu\u003ea\u003c/u\u003eo wa\u003cb\u003eA\u003c/b\u003ell\u003cu\u003ea\u003c/u\u003ehu AAaleemun \u003cu\u003eh\u003c/u\u003eakeem\u003cb\u003eun\u003c/b\u003e"
    },
    {
        "BookCode":  "TLT",
        "SurahNumber":  "9",
        "AyahNumber":  "16",
        "Recitation":  "Alafasy_128kbps/009016",
        "Body":  "Am \u003cu\u003eh\u003c/u\u003easibtum an tutrakoo walamm\u003cu\u003ea\u003c/u\u003e yaAAlami All\u003cu\u003ea\u003c/u\u003ehu alla\u003cu\u003eth\u003c/u\u003eeena j\u003cu\u003ea\u003c/u\u003ehadoo minkum walam yattakhi\u003cu\u003eth\u003c/u\u003eoo min dooni All\u003cu\u003ea\u003c/u\u003ehi wal\u003cu\u003ea\u003c/u\u003e rasoolihi wal\u003cu\u003ea\u003c/u\u003e almumineena waleejatan wa\u003cb\u003eA\u003c/b\u003ell\u003cu\u003ea\u003c/u\u003ehu khabeerun bim\u003cu\u003ea\u003c/u\u003e taAAmaloon\u003cb\u003ea\u003c/b\u003e"
    },
    {
        "BookCode":  "TLT",
        "SurahNumber":  "9",
        "AyahNumber":  "17",
        "Recitation":  "Alafasy_128kbps/009017",
        "Body":  "M\u003cu\u003ea\u003c/u\u003e k\u003cu\u003ea\u003c/u\u003ena lilmushrikeena an yaAAmuroo mas\u003cu\u003ea\u003c/u\u003ejida All\u003cu\u003ea\u003c/u\u003ehi sh\u003cu\u003ea\u003c/u\u003ehideena AAal\u003cu\u003ea\u003c/u\u003e anfusihim bi\u003cb\u003ea\u003c/b\u003elkufri ol\u003cu\u003ea\u003c/u\u003eika \u003cu\u003eh\u003c/u\u003eabi\u003cu\u003et\u003c/u\u003eat aAAm\u003cu\u003ea\u003c/u\u003eluhum wafee a\u003cb\u003el\u003c/b\u003enn\u003cu\u003ea\u003c/u\u003eri hum kh\u003cu\u003ea\u003c/u\u003elidoon\u003cb\u003ea\u003c/b\u003e"
    },
    {
        "BookCode":  "TLT",
        "SurahNumber":  "9",
        "AyahNumber":  "18",
        "Recitation":  "Alafasy_128kbps/009018",
        "Body":  "Innam\u003cu\u003ea\u003c/u\u003e yaAAmuru mas\u003cu\u003ea\u003c/u\u003ejida All\u003cu\u003ea\u003c/u\u003ehi man \u003cu\u003ea\u003c/u\u003emana bi\u003cb\u003eA\u003c/b\u003ell\u003cu\u003ea\u003c/u\u003ehi wa\u003cb\u003ea\u003c/b\u003elyawmi al\u003cu\u003ea\u003c/u\u003ekhiri waaq\u003cu\u003ea\u003c/u\u003ema a\u003cb\u003el\u003c/b\u003e\u003cu\u003ess\u003c/u\u003eal\u003cu\u003ea\u003c/u\u003eta wa\u003cu\u003ea\u003c/u\u003et\u003cu\u003ea\u003c/u\u003e a\u003cb\u003el\u003c/b\u003ezzak\u003cu\u003ea\u003c/u\u003eta walam yakhsha ill\u003cu\u003ea\u003c/u\u003e All\u003cu\u003ea\u003c/u\u003eha faAAas\u003cu\u003ea\u003c/u\u003e ol\u003cu\u003ea\u003c/u\u003eika an yakoonoo mina almuhtadeen\u003cb\u003ea\u003c/b\u003e"
    },
    {
        "BookCode":  "TLT",
        "SurahNumber":  "9",
        "AyahNumber":  "19",
        "Recitation":  "Alafasy_128kbps/009019",
        "Body":  "AjaAAaltum siq\u003cu\u003ea\u003c/u\u003eyata al\u003cu\u003eha\u003c/u\u003ejji waAAim\u003cu\u003ea\u003c/u\u003erata almasjidi al\u003cu\u003eh\u003c/u\u003ear\u003cu\u003ea\u003c/u\u003emi kaman \u003cu\u003ea\u003c/u\u003emana bi\u003cb\u003eA\u003c/b\u003ell\u003cu\u003ea\u003c/u\u003ehi wa\u003cb\u003ea\u003c/b\u003elyawmi al\u003cu\u003ea\u003c/u\u003ekhiri waj\u003cu\u003ea\u003c/u\u003ehada fee sabeeli All\u003cu\u003ea\u003c/u\u003ehi l\u003cu\u003ea\u003c/u\u003e yastawoona AAinda All\u003cu\u003ea\u003c/u\u003ehi wa\u003cb\u003eA\u003c/b\u003ell\u003cu\u003ea\u003c/u\u003ehu l\u003cu\u003ea\u003c/u\u003e yahdee alqawma a\u003cb\u003el\u003c/b\u003e\u003ci\u003e\u003cu\u003ethth\u003c/u\u003e\u003c/i\u003e\u003cu\u003ea\u003c/u\u003elimeen\u003cb\u003ea\u003c/b\u003e"
    },
    {
        "BookCode":  "TLT",
        "SurahNumber":  "9",
        "AyahNumber":  "2",
        "Recitation":  "Alafasy_128kbps/009002",
        "Body":  "Fasee\u003cu\u003eh\u003c/u\u003eoo fee alar\u003cu\u003ed\u003c/u\u003ei arbaAAata ashhurin wa\u003cb\u003ei\u003c/b\u003eAAlamoo annakum ghayru muAAjizee All\u003cu\u003ea\u003c/u\u003ehi waanna All\u003cu\u003ea\u003c/u\u003eha mukhzee alk\u003cu\u003ea\u003c/u\u003efireen\u003cb\u003ea\u003c/b\u003e"
    },
    {
        "BookCode":  "TLT",
        "SurahNumber":  "9",
        "AyahNumber":  "20",
        "Recitation":  "Alafasy_128kbps/009020",
        "Body":  "Alla\u003cu\u003eth\u003c/u\u003eeena \u003cu\u003ea\u003c/u\u003emanoo wah\u003cu\u003ea\u003c/u\u003ejaroo waj\u003cu\u003ea\u003c/u\u003ehadoo fee sabeeli All\u003cu\u003ea\u003c/u\u003ehi biamw\u003cu\u003ea\u003c/u\u003elihim waanfusihim aAA\u003ci\u003e\u003cu\u003eth\u003c/u\u003e\u003c/i\u003eamu darajatan AAinda All\u003cu\u003ea\u003c/u\u003ehi waol\u003cu\u003ea\u003c/u\u003eika humu alf\u003cu\u003ea\u003c/u\u003eizoon\u003cb\u003ea\u003c/b\u003e"
    },
    {
        "BookCode":  "TLT",
        "SurahNumber":  "9",
        "AyahNumber":  "21",
        "Recitation":  "Alafasy_128kbps/009021",
        "Body":  "Yubashshiruhum rabbuhum bira\u003cu\u003eh\u003c/u\u003ematin minhu wari\u003cu\u003ed\u003c/u\u003ew\u003cu\u003ea\u003c/u\u003enin wajann\u003cu\u003ea\u003c/u\u003etin lahum feeh\u003cu\u003ea\u003c/u\u003e naAAeemun muqeem\u003cb\u003eun\u003c/b\u003e"
    },
    {
        "BookCode":  "TLT",
        "SurahNumber":  "9",
        "AyahNumber":  "22",
        "Recitation":  "Alafasy_128kbps/009022",
        "Body":  "Kh\u003cu\u003ea\u003c/u\u003elideena feeh\u003cu\u003ea\u003c/u\u003e abadan inna All\u003cu\u003ea\u003c/u\u003eha AAindahu ajrun AAa\u003ci\u003e\u003cu\u003eth\u003c/u\u003e\u003c/i\u003eeem\u003cb\u003eun\u003c/b\u003e"
    },
    {
        "BookCode":  "TLT",
        "SurahNumber":  "9",
        "AyahNumber":  "23",
        "Recitation":  "Alafasy_128kbps/009023",
        "Body":  "Y\u003cu\u003ea\u003c/u\u003e ayyuh\u003cu\u003ea\u003c/u\u003e alla\u003cu\u003eth\u003c/u\u003eeena \u003cu\u003ea\u003c/u\u003emanoo l\u003cu\u003ea\u003c/u\u003e tattakhi\u003cu\u003eth\u003c/u\u003eoo \u003cu\u003ea\u003c/u\u003eb\u003cu\u003ea\u003c/u\u003eakum waikhw\u003cu\u003ea\u003c/u\u003enakum awliy\u003cu\u003ea\u003c/u\u003ea ini ista\u003cu\u003eh\u003c/u\u003eabboo alkufra AAal\u003cu\u003ea\u003c/u\u003e aleem\u003cu\u003ea\u003c/u\u003eni waman yatawallahum minkum faol\u003cu\u003ea\u003c/u\u003eika humu a\u003cb\u003el\u003c/b\u003e\u003ci\u003e\u003cu\u003ethth\u003c/u\u003e\u003c/i\u003e\u003cu\u003ea\u003c/u\u003elimoon\u003cb\u003ea\u003c/b\u003e"
    },
    {
        "BookCode":  "TLT",
        "SurahNumber":  "9",
        "AyahNumber":  "24",
        "Recitation":  "Alafasy_128kbps/009024",
        "Body":  "Qul in k\u003cu\u003ea\u003c/u\u003ena \u003cu\u003ea\u003c/u\u003eb\u003cu\u003ea\u003c/u\u003eokum waabn\u003cu\u003ea\u003c/u\u003eokum waikhw\u003cu\u003ea\u003c/u\u003enukum waazw\u003cu\u003ea\u003c/u\u003ejukum waAAasheeratukum waamw\u003cu\u003ea\u003c/u\u003elun iqtaraftumooh\u003cu\u003ea\u003c/u\u003e watij\u003cu\u003ea\u003c/u\u003eratun takhshawna kas\u003cu\u003ea\u003c/u\u003edah\u003cu\u003ea\u003c/u\u003e wamas\u003cu\u003ea\u003c/u\u003ekinu tar\u003cu\u003ed\u003c/u\u003eawnah\u003cu\u003ea\u003c/u\u003e a\u003cu\u003eh\u003c/u\u003eabba ilaykum mina All\u003cu\u003ea\u003c/u\u003ehi warasoolihi wajih\u003cu\u003ea\u003c/u\u003edin fee sabeelihi fatarabba\u003cu\u003es\u003c/u\u003eoo \u003cu\u003eh\u003c/u\u003eatt\u003cu\u003ea\u003c/u\u003e yatiya All\u003cu\u003ea\u003c/u\u003ehu biamrihi wa\u003cb\u003eA\u003c/b\u003ell\u003cu\u003ea\u003c/u\u003ehu l\u003cu\u003ea\u003c/u\u003e yahdee alqawma alf\u003cu\u003ea\u003c/u\u003esiqeen\u003cb\u003ea\u003c/b\u003e"
    },
    {
        "BookCode":  "TLT",
        "SurahNumber":  "9",
        "AyahNumber":  "25",
        "Recitation":  "Alafasy_128kbps/009025",
        "Body":  "Laqad na\u003cu\u003es\u003c/u\u003earakumu All\u003cu\u003ea\u003c/u\u003ehu fee maw\u003cu\u003eat\u003c/u\u003eina katheeratin wayawma \u003cu\u003eh\u003c/u\u003eunaynin i\u003cu\u003eth\u003c/u\u003e aAAjabatkum kathratukum falam tughni AAankum shayan wa\u003cu\u003eda\u003c/u\u003eqat AAalaykumu alar\u003cu\u003ed\u003c/u\u003eu bim\u003cu\u003ea\u003c/u\u003e ra\u003cu\u003eh\u003c/u\u003eubat thumma wallaytum mudbireen\u003cb\u003ea\u003c/b\u003e"
    },
    {
        "BookCode":  "TLT",
        "SurahNumber":  "9",
        "AyahNumber":  "26",
        "Recitation":  "Alafasy_128kbps/009026",
        "Body":  "Thumma anzala All\u003cu\u003ea\u003c/u\u003ehu sakeenatahu AAal\u003cu\u003ea\u003c/u\u003e rasoolihi waAAal\u003cu\u003ea\u003c/u\u003e almumineena waanzala junoodan lam tarawh\u003cu\u003ea\u003c/u\u003e waAAa\u003cu\u003ethth\u003c/u\u003eaba alla\u003cu\u003eth\u003c/u\u003eeena kafaroo wa\u003cu\u003etha\u003c/u\u003elika jaz\u003cu\u003ea\u003c/u\u003eo alk\u003cu\u003ea\u003c/u\u003efireen\u003cb\u003ea\u003c/b\u003e"
    },
    {
        "BookCode":  "TLT",
        "SurahNumber":  "9",
        "AyahNumber":  "27",
        "Recitation":  "Alafasy_128kbps/009027",
        "Body":  "Thumma yatoobu All\u003cu\u003ea\u003c/u\u003ehu min baAAdi \u003cu\u003etha\u003c/u\u003elika AAal\u003cu\u003ea\u003c/u\u003e man yash\u003cu\u003ea\u003c/u\u003eo wa\u003cb\u003eA\u003c/b\u003ell\u003cu\u003ea\u003c/u\u003ehu ghafoorun ra\u003cu\u003eh\u003c/u\u003eeem\u003cb\u003eun\u003c/b\u003e"
    },
    {
        "BookCode":  "TLT",
        "SurahNumber":  "9",
        "AyahNumber":  "28",
        "Recitation":  "Alafasy_128kbps/009028",
        "Body":  "Y\u003cu\u003ea\u003c/u\u003e ayyuh\u003cu\u003ea\u003c/u\u003e alla\u003cu\u003eth\u003c/u\u003eeena \u003cu\u003ea\u003c/u\u003emanoo innam\u003cu\u003ea\u003c/u\u003e almushrikoona najasun fal\u003cu\u003ea\u003c/u\u003e yaqraboo almasjida al\u003cu\u003eh\u003c/u\u003ear\u003cu\u003ea\u003c/u\u003ema baAAda AA\u003cu\u003ea\u003c/u\u003emihim h\u003cu\u003eatha\u003c/u\u003e wain khiftum AAaylatan fasawfa yughneekumu All\u003cu\u003ea\u003c/u\u003ehu min fa\u003cu\u003ed\u003c/u\u003elihi in sh\u003cu\u003ea\u003c/u\u003ea inna All\u003cu\u003ea\u003c/u\u003eha AAaleemun \u003cu\u003eh\u003c/u\u003eakeem\u003cb\u003eun\u003c/b\u003e"
    },
    {
        "BookCode":  "TLT",
        "SurahNumber":  "9",
        "AyahNumber":  "29",
        "Recitation":  "Alafasy_128kbps/009029",
        "Body":  "Q\u003cu\u003ea\u003c/u\u003etiloo alla\u003cu\u003eth\u003c/u\u003eeena l\u003cu\u003ea\u003c/u\u003e yuminoona bi\u003cb\u003eA\u003c/b\u003ell\u003cu\u003ea\u003c/u\u003ehi wal\u003cu\u003ea\u003c/u\u003e bi\u003cb\u003ea\u003c/b\u003elyawmi al\u003cu\u003ea\u003c/u\u003ekhiri wal\u003cu\u003ea\u003c/u\u003e yu\u003cu\u003eh\u003c/u\u003earrimoona m\u003cu\u003ea\u003c/u\u003e \u003cu\u003eh\u003c/u\u003earrama All\u003cu\u003ea\u003c/u\u003ehu warasooluhu wal\u003cu\u003ea\u003c/u\u003e yadeenoona deena al\u003cu\u003eh\u003c/u\u003eaqqi mina alla\u003cu\u003eth\u003c/u\u003eeena ootoo alkit\u003cu\u003ea\u003c/u\u003eba \u003cu\u003eh\u003c/u\u003eatt\u003cu\u003ea\u003c/u\u003e yuAA\u003cu\u003et\u003c/u\u003eoo aljizyata AAan yadin wahum \u003cu\u003esa\u003c/u\u003eghiroon\u003cb\u003ea\u003c/b\u003e"
    },
    {
        "BookCode":  "TLT",
        "SurahNumber":  "9",
        "AyahNumber":  "3",
        "Recitation":  "Alafasy_128kbps/009003",
        "Body":  "Waa\u003cu\u003etha\u003c/u\u003enun mina All\u003cu\u003ea\u003c/u\u003ehi warasoolihi il\u003cu\u003ea\u003c/u\u003e a\u003cb\u003el\u003c/b\u003enn\u003cu\u003ea\u003c/u\u003esi yawma al\u003cu\u003eh\u003c/u\u003eajji alakbari anna All\u003cu\u003ea\u003c/u\u003eha bareeon mina almushrikeena warasooluhu fain tubtum fahuwa khayrun lakum wain tawallaytum fa\u003cb\u003ei\u003c/b\u003eAAlamoo annakum ghayru muAAjizee All\u003cu\u003ea\u003c/u\u003ehi wabashshiri alla\u003cu\u003eth\u003c/u\u003eeena kafaroo biAAa\u003cu\u003etha\u003c/u\u003ebin aleem\u003cb\u003ein\u003c/b\u003e"
    },
    {
        "BookCode":  "TLT",
        "SurahNumber":  "9",
        "AyahNumber":  "30",
        "Recitation":  "Alafasy_128kbps/009030",
        "Body":  "Waq\u003cu\u003ea\u003c/u\u003elati alyahoodu AAuzayrun ibnu All\u003cu\u003ea\u003c/u\u003ehi waq\u003cu\u003ea\u003c/u\u003elati a\u003cb\u003el\u003c/b\u003enna\u003cu\u003esa\u003c/u\u003er\u003cu\u003ea\u003c/u\u003e almasee\u003cu\u003eh\u003c/u\u003eu ibnu All\u003cu\u003ea\u003c/u\u003ehi \u003cu\u003etha\u003c/u\u003elika qawluhum biafw\u003cu\u003ea\u003c/u\u003ehihim yu\u003cu\u003eda\u003c/u\u003ehioona qawla alla\u003cu\u003eth\u003c/u\u003eeena kafaroo min qablu q\u003cu\u003ea\u003c/u\u003etalahumu All\u003cu\u003ea\u003c/u\u003ehu ann\u003cu\u003ea\u003c/u\u003e yufakoon\u003cb\u003ea\u003c/b\u003e"
    },
    {
        "BookCode":  "TLT",
        "SurahNumber":  "9",
        "AyahNumber":  "31",
        "Recitation":  "Alafasy_128kbps/009031",
        "Body":  "Ittakha\u003cu\u003eth\u003c/u\u003eoo a\u003cu\u003eh\u003c/u\u003eb\u003cu\u003ea\u003c/u\u003erahum waruhb\u003cu\u003ea\u003c/u\u003enahum arb\u003cu\u003ea\u003c/u\u003eban min dooni All\u003cu\u003ea\u003c/u\u003ehi wa\u003cb\u003ea\u003c/b\u003elmasee\u003cu\u003eh\u003c/u\u003ea ibna maryama wam\u003cu\u003ea\u003c/u\u003e omiroo ill\u003cu\u003ea\u003c/u\u003e liyaAAbudoo il\u003cu\u003ea\u003c/u\u003ehan w\u003cu\u003eah\u003c/u\u003eidan l\u003cu\u003ea\u003c/u\u003e il\u003cu\u003ea\u003c/u\u003eha ill\u003cu\u003ea\u003c/u\u003e huwa sub\u003cu\u003eha\u003c/u\u003enahu AAamm\u003cu\u003ea\u003c/u\u003e yushrikoon\u003cb\u003ea\u003c/b\u003e"
    },
    {
        "BookCode":  "TLT",
        "SurahNumber":  "9",
        "AyahNumber":  "32",
        "Recitation":  "Alafasy_128kbps/009032",
        "Body":  "Yureedoona an yu\u003cu\u003et\u003c/u\u003efioo noora All\u003cu\u003ea\u003c/u\u003ehi biafw\u003cu\u003ea\u003c/u\u003ehihim wayab\u003cu\u003ea\u003c/u\u003e All\u003cu\u003ea\u003c/u\u003ehu ill\u003cu\u003ea\u003c/u\u003e an yutimma noorahu walaw kariha alk\u003cu\u003ea\u003c/u\u003efiroon\u003cb\u003ea\u003c/b\u003e"
    },
    {
        "BookCode":  "TLT",
        "SurahNumber":  "9",
        "AyahNumber":  "33",
        "Recitation":  "Alafasy_128kbps/009033",
        "Body":  "Huwa alla\u003cu\u003eth\u003c/u\u003eee arsala rasoolahu bi\u003cb\u003ea\u003c/b\u003elhud\u003cu\u003ea\u003c/u\u003e wadeeni al\u003cu\u003eh\u003c/u\u003eaqqi liyu\u003ci\u003e\u003cu\u003eth\u003c/u\u003e\u003c/i\u003ehirahu AAal\u003cu\u003ea\u003c/u\u003e a\u003cb\u003el\u003c/b\u003eddeeni kullihi walaw kariha almushrikoon\u003cb\u003ea\u003c/b\u003e"
    },
    {
        "BookCode":  "TLT",
        "SurahNumber":  "9",
        "AyahNumber":  "34",
        "Recitation":  "Alafasy_128kbps/009034",
        "Body":  "Y\u003cu\u003ea\u003c/u\u003e ayyuh\u003cu\u003ea\u003c/u\u003e alla\u003cu\u003eth\u003c/u\u003eeena \u003cu\u003ea\u003c/u\u003emanoo inna katheeran mina ala\u003cu\u003eh\u003c/u\u003eb\u003cu\u003ea\u003c/u\u003eri wa\u003cb\u003eal\u003c/b\u003erruhb\u003cu\u003ea\u003c/u\u003eni layakuloona amw\u003cu\u003ea\u003c/u\u003ela a\u003cb\u003el\u003c/b\u003enn\u003cu\u003ea\u003c/u\u003esi bi\u003cb\u003ea\u003c/b\u003elb\u003cu\u003eat\u003c/u\u003eili waya\u003cu\u003es\u003c/u\u003euddoona AAan sabeeli All\u003cu\u003ea\u003c/u\u003ehi wa\u003cb\u003ea\u003c/b\u003ella\u003cu\u003eth\u003c/u\u003eeena yaknizoona a\u003cb\u003el\u003c/b\u003e\u003cu\u003ethth\u003c/u\u003eahaba wa\u003cb\u003ea\u003c/b\u003elfi\u003cu\u003edd\u003c/u\u003eata wal\u003cu\u003ea\u003c/u\u003e yunfiqoonah\u003cu\u003ea\u003c/u\u003e fee sabeeli All\u003cu\u003ea\u003c/u\u003ehi fabashshirhum biAAa\u003cu\u003etha\u003c/u\u003ebin aleem\u003cb\u003ein\u003c/b\u003e"
    },
    {
        "BookCode":  "TLT",
        "SurahNumber":  "9",
        "AyahNumber":  "35",
        "Recitation":  "Alafasy_128kbps/009035",
        "Body":  "Yawma yu\u003cu\u003eh\u003c/u\u003em\u003cu\u003ea\u003c/u\u003e AAalayh\u003cu\u003ea\u003c/u\u003e fee n\u003cu\u003ea\u003c/u\u003eri jahannama fatukw\u003cu\u003ea\u003c/u\u003e bih\u003cu\u003ea\u003c/u\u003e jib\u003cu\u003ea\u003c/u\u003ehuhum wajunoobuhum wa\u003ci\u003e\u003cu\u003eth\u003c/u\u003e\u003c/i\u003euhooruhum h\u003cu\u003eatha\u003c/u\u003e m\u003cu\u003ea\u003c/u\u003e kanaztum lianfusikum fa\u003cu\u003eth\u003c/u\u003eooqoo m\u003cu\u003ea\u003c/u\u003e kuntum taknizoon\u003cb\u003ea\u003c/b\u003e"
    },
    {
        "BookCode":  "TLT",
        "SurahNumber":  "9",
        "AyahNumber":  "36",
        "Recitation":  "Alafasy_128kbps/009036",
        "Body":  "Inna AAiddata a\u003cb\u003el\u003c/b\u003eshshuhoori AAinda All\u003cu\u003ea\u003c/u\u003ehi ithn\u003cu\u003ea\u003c/u\u003e AAashara shahran fee kit\u003cu\u003ea\u003c/u\u003ebi All\u003cu\u003ea\u003c/u\u003ehi yawma khalaqa a\u003cb\u003el\u003c/b\u003essam\u003cu\u003ea\u003c/u\u003ew\u003cu\u003ea\u003c/u\u003eti wa\u003cb\u003ea\u003c/b\u003elar\u003cu\u003ed\u003c/u\u003ea minh\u003cu\u003ea\u003c/u\u003e arbaAAatun \u003cu\u003eh\u003c/u\u003eurumun \u003cu\u003etha\u003c/u\u003elika a\u003cb\u003el\u003c/b\u003eddeenu alqayyimu fal\u003cu\u003ea\u003c/u\u003e ta\u003ci\u003e\u003cu\u003eth\u003c/u\u003e\u003c/i\u003elimoo feehinna anfusakum waq\u003cu\u003ea\u003c/u\u003etiloo almushrikeena k\u003cu\u003ea\u003c/u\u003effatan kam\u003cu\u003ea\u003c/u\u003e yuq\u003cu\u003ea\u003c/u\u003etiloonakum k\u003cu\u003ea\u003c/u\u003effatan wa\u003cb\u003ei\u003c/b\u003eAAlamoo anna All\u003cu\u003ea\u003c/u\u003eha maAAa almuttaqeen\u003cb\u003ea\u003c/b\u003e"
    },
    {
        "BookCode":  "TLT",
        "SurahNumber":  "9",
        "AyahNumber":  "37",
        "Recitation":  "Alafasy_128kbps/009037",
        "Body":  "Innam\u003cu\u003ea\u003c/u\u003e a\u003cb\u003el\u003c/b\u003ennaseeo ziy\u003cu\u003ea\u003c/u\u003edatun fee alkufri yu\u003cu\u003ed\u003c/u\u003eallu bihi alla\u003cu\u003eth\u003c/u\u003eeena kafaroo yu\u003cu\u003eh\u003c/u\u003eilloonahu AA\u003cu\u003ea\u003c/u\u003eman wayu\u003cu\u003eh\u003c/u\u003earrimoonahu AA\u003cu\u003ea\u003c/u\u003eman liyuw\u003cu\u003eat\u003c/u\u003eioo AAiddata m\u003cu\u003ea\u003c/u\u003e \u003cu\u003eh\u003c/u\u003earrama All\u003cu\u003ea\u003c/u\u003ehu fayu\u003cu\u003eh\u003c/u\u003eilloo m\u003cu\u003ea\u003c/u\u003e \u003cu\u003eh\u003c/u\u003earrama All\u003cu\u003ea\u003c/u\u003ehu zuyyina lahum sooo aAAm\u003cu\u003ea\u003c/u\u003elihim wa\u003cb\u003eA\u003c/b\u003ell\u003cu\u003ea\u003c/u\u003ehu l\u003cu\u003ea\u003c/u\u003e yahdee alqawma alk\u003cu\u003ea\u003c/u\u003efireen\u003cb\u003ea\u003c/b\u003e"
    },
    {
        "BookCode":  "TLT",
        "SurahNumber":  "9",
        "AyahNumber":  "38",
        "Recitation":  "Alafasy_128kbps/009038",
        "Body":  "Y\u003cu\u003ea\u003c/u\u003e ayyuh\u003cu\u003ea\u003c/u\u003e alla\u003cu\u003eth\u003c/u\u003eeena \u003cu\u003ea\u003c/u\u003emanoo m\u003cu\u003ea\u003c/u\u003e lakum i\u003cu\u003etha\u003c/u\u003e qeela lakumu infiroo fee sabeeli All\u003cu\u003ea\u003c/u\u003ehi ithth\u003cu\u003ea\u003c/u\u003eqaltum il\u003cu\u003ea\u003c/u\u003e alar\u003cu\u003ed\u003c/u\u003ei ara\u003cu\u003ed\u003c/u\u003eeetum bi\u003cb\u003ea\u003c/b\u003el\u003cu\u003eh\u003c/u\u003eay\u003cu\u003ea\u003c/u\u003eti a\u003cb\u003el\u003c/b\u003edduny\u003cu\u003ea\u003c/u\u003e mina al\u003cu\u003ea\u003c/u\u003ekhirati fam\u003cu\u003ea\u003c/u\u003e mat\u003cu\u003ea\u003c/u\u003eAAu al\u003cu\u003eh\u003c/u\u003eay\u003cu\u003ea\u003c/u\u003eti a\u003cb\u003el\u003c/b\u003edduny\u003cu\u003ea\u003c/u\u003e fee al\u003cu\u003ea\u003c/u\u003ekhirati ill\u003cu\u003ea\u003c/u\u003e qaleel\u003cb\u003eun\u003c/b\u003e"
    },
    {
        "BookCode":  "TLT",
        "SurahNumber":  "9",
        "AyahNumber":  "39",
        "Recitation":  "Alafasy_128kbps/009039",
        "Body":  "Ill\u003cu\u003ea\u003c/u\u003e tanfiroo yuAAa\u003cu\u003ethth\u003c/u\u003eibkum AAa\u003cu\u003etha\u003c/u\u003eban aleeman wayastabdil qawman ghayrakum wal\u003cu\u003ea\u003c/u\u003e ta\u003cu\u003ed\u003c/u\u003eurroohu shayan wa\u003cb\u003eA\u003c/b\u003ell\u003cu\u003ea\u003c/u\u003ehu AAal\u003cu\u003ea\u003c/u\u003e kulli shayin qadeer\u003cb\u003eun\u003c/b\u003e"
    },
    {
        "BookCode":  "TLT",
        "SurahNumber":  "9",
        "AyahNumber":  "4",
        "Recitation":  "Alafasy_128kbps/009004",
        "Body":  "Ill\u003cu\u003ea\u003c/u\u003e alla\u003cu\u003eth\u003c/u\u003eeena AA\u003cu\u003ea\u003c/u\u003ehadtum mina almushrikeena thumma lam yanqu\u003cu\u003es\u003c/u\u003eookum shayan walam yu\u003ci\u003e\u003cu\u003eth\u003c/u\u003e\u003c/i\u003e\u003cu\u003ea\u003c/u\u003ehiroo AAalaykum a\u003cu\u003eh\u003c/u\u003eadan faatimmoo ilayhim AAahdahum il\u003cu\u003ea\u003c/u\u003e muddatihim inna All\u003cu\u003ea\u003c/u\u003eha yu\u003cu\u003eh\u003c/u\u003eibbu almuttaqeen\u003cb\u003ea\u003c/b\u003e"
    },
    {
        "BookCode":  "TLT",
        "SurahNumber":  "9",
        "AyahNumber":  "40",
        "Recitation":  "Alafasy_128kbps/009040",
        "Body":  "Ill\u003cu\u003ea\u003c/u\u003e tan\u003cu\u003es\u003c/u\u003euroohu faqad na\u003cu\u003es\u003c/u\u003earahu All\u003cu\u003ea\u003c/u\u003ehu i\u003cu\u003eth\u003c/u\u003e akhrajahu alla\u003cu\u003eth\u003c/u\u003eeena kafaroo th\u003cu\u003ea\u003c/u\u003eniya ithnayni i\u003cu\u003eth\u003c/u\u003e hum\u003cu\u003ea\u003c/u\u003e fee algh\u003cu\u003ea\u003c/u\u003eri i\u003cu\u003eth\u003c/u\u003e yaqoolu li\u003cu\u003esah\u003c/u\u003eibihi l\u003cu\u003ea\u003c/u\u003e ta\u003cu\u003eh\u003c/u\u003ezan inna All\u003cu\u003ea\u003c/u\u003eha maAAan\u003cu\u003ea\u003c/u\u003e faanzala All\u003cu\u003ea\u003c/u\u003ehu sakeenatahu AAalayhi waayyadahu bijunoodin lam tarawh\u003cu\u003ea\u003c/u\u003e wajaAAala kalimata alla\u003cu\u003eth\u003c/u\u003eeena kafaroo a\u003cb\u003el\u003c/b\u003essufl\u003cu\u003ea\u003c/u\u003e wakalimatu All\u003cu\u003ea\u003c/u\u003ehi hiya alAAuly\u003cu\u003ea\u003c/u\u003e wa\u003cb\u003eA\u003c/b\u003ell\u003cu\u003ea\u003c/u\u003ehu AAazeezun \u003cu\u003eh\u003c/u\u003eakeem\u003cb\u003eun\u003c/b\u003e"
    },
    {
        "BookCode":  "TLT",
        "SurahNumber":  "9",
        "AyahNumber":  "41",
        "Recitation":  "Alafasy_128kbps/009041",
        "Body":  "Infiroo khif\u003cu\u003ea\u003c/u\u003efan wathiq\u003cu\u003ea\u003c/u\u003elan waj\u003cu\u003ea\u003c/u\u003ehidoo biamw\u003cu\u003ea\u003c/u\u003elikum waanfusikum fee sabeeli All\u003cu\u003ea\u003c/u\u003ehi \u003cu\u003etha\u003c/u\u003elikum khayrun lakum in kuntum taAAlamoon\u003cb\u003ea\u003c/b\u003e"
    },
    {
        "BookCode":  "TLT",
        "SurahNumber":  "9",
        "AyahNumber":  "42",
        "Recitation":  "Alafasy_128kbps/009042",
        "Body":  "Law k\u003cu\u003ea\u003c/u\u003ena AAara\u003cu\u003ed\u003c/u\u003ean qareeban wasafaran q\u003cu\u003eas\u003c/u\u003eidan la\u003cb\u003ei\u003c/b\u003ettabaAAooka wal\u003cu\u003ea\u003c/u\u003ekin baAAudat AAalayhimu a\u003cb\u003el\u003c/b\u003eshshuqqatu wasaya\u003cu\u003eh\u003c/u\u003elifoona bi\u003cb\u003eA\u003c/b\u003ell\u003cu\u003ea\u003c/u\u003ehi lawi ista\u003cu\u003et\u003c/u\u003eaAAn\u003cu\u003ea\u003c/u\u003e lakharajn\u003cu\u003ea\u003c/u\u003e maAAakum yuhlikoona anfusahum wa\u003cb\u003eA\u003c/b\u003ell\u003cu\u003ea\u003c/u\u003ehu yaAAlamu innahum lak\u003cu\u003eath\u003c/u\u003eiboon\u003cb\u003ea\u003c/b\u003e"
    },
    {
        "BookCode":  "TLT",
        "SurahNumber":  "9",
        "AyahNumber":  "43",
        "Recitation":  "Alafasy_128kbps/009043",
        "Body":  "AAaf\u003cu\u003ea\u003c/u\u003e All\u003cu\u003ea\u003c/u\u003ehu AAanka lima a\u003cu\u003eth\u003c/u\u003einta lahum \u003cu\u003eh\u003c/u\u003eatt\u003cu\u003ea\u003c/u\u003e yatabayyana laka alla\u003cu\u003eth\u003c/u\u003eeena \u003cu\u003es\u003c/u\u003eadaqoo wataAAlama alk\u003cu\u003eath\u003c/u\u003eibeen\u003cb\u003ea\u003c/b\u003e"
    },
    {
        "BookCode":  "TLT",
        "SurahNumber":  "9",
        "AyahNumber":  "44",
        "Recitation":  "Alafasy_128kbps/009044",
        "Body":  "L\u003cu\u003ea\u003c/u\u003e yasta\u003cu\u003eth\u003c/u\u003einuka alla\u003cu\u003eth\u003c/u\u003eeena yuminoona bi\u003cb\u003eA\u003c/b\u003ell\u003cu\u003ea\u003c/u\u003ehi wa\u003cb\u003ea\u003c/b\u003elyawmi al\u003cu\u003ea\u003c/u\u003ekhiri an yuj\u003cu\u003ea\u003c/u\u003ehidoo biamw\u003cu\u003ea\u003c/u\u003elihim waanfusihim wa\u003cb\u003eA\u003c/b\u003ell\u003cu\u003ea\u003c/u\u003ehu AAaleemun bi\u003cb\u003ea\u003c/b\u003elmuttaqeen\u003cb\u003ea\u003c/b\u003e"
    },
    {
        "BookCode":  "TLT",
        "SurahNumber":  "9",
        "AyahNumber":  "45",
        "Recitation":  "Alafasy_128kbps/009045",
        "Body":  "Innam\u003cu\u003ea\u003c/u\u003e yasta\u003cu\u003eth\u003c/u\u003einuka alla\u003cu\u003eth\u003c/u\u003eeena l\u003cu\u003ea\u003c/u\u003e yuminoona bi\u003cb\u003eA\u003c/b\u003ell\u003cu\u003ea\u003c/u\u003ehi wa\u003cb\u003ea\u003c/b\u003elyawmi al\u003cu\u003ea\u003c/u\u003ekhiri wa\u003cb\u003ei\u003c/b\u003ert\u003cu\u003ea\u003c/u\u003ebat quloobuhum fahum fee raybihim yataraddadoon\u003cb\u003ea\u003c/b\u003e"
    },
    {
        "BookCode":  "TLT",
        "SurahNumber":  "9",
        "AyahNumber":  "46",
        "Recitation":  "Alafasy_128kbps/009046",
        "Body":  "Walaw ar\u003cu\u003ea\u003c/u\u003edoo alkhurooja laaAAaddoo lahu AAuddatan wal\u003cu\u003ea\u003c/u\u003ekin kariha All\u003cu\u003ea\u003c/u\u003ehu inbiAA\u003cu\u003ea\u003c/u\u003ethahum fathabba\u003cu\u003et\u003c/u\u003eahum waqeela oqAAudoo maAAa alq\u003cu\u003ea\u003c/u\u003eAAideen\u003cb\u003ea\u003c/b\u003e"
    },
    {
        "BookCode":  "TLT",
        "SurahNumber":  "9",
        "AyahNumber":  "47",
        "Recitation":  "Alafasy_128kbps/009047",
        "Body":  "Law kharajoo feekum m\u003cu\u003ea\u003c/u\u003e z\u003cu\u003ea\u003c/u\u003edookum ill\u003cu\u003ea\u003c/u\u003e khab\u003cu\u003ea\u003c/u\u003elan walaaw\u003cu\u003ed\u003c/u\u003eaAAoo khil\u003cu\u003ea\u003c/u\u003elakum yabghoonakumu alfitnata wafeekum samm\u003cu\u003ea\u003c/u\u003eAAoona lahum wa\u003cb\u003eA\u003c/b\u003ell\u003cu\u003ea\u003c/u\u003ehu AAaleemun bi\u003cb\u003eal\u003c/b\u003e\u003ci\u003e\u003cu\u003ethth\u003c/u\u003e\u003c/i\u003e\u003cu\u003ea\u003c/u\u003elimeen\u003cb\u003ea\u003c/b\u003e"
    },
    {
        "BookCode":  "TLT",
        "SurahNumber":  "9",
        "AyahNumber":  "48",
        "Recitation":  "Alafasy_128kbps/009048",
        "Body":  "Laqadi ibtaghawoo alfitnata min qablu waqallaboo laka alomoora \u003cu\u003eh\u003c/u\u003eatt\u003cu\u003ea\u003c/u\u003e j\u003cu\u003ea\u003c/u\u003ea al\u003cu\u003eh\u003c/u\u003eaqqu wa\u003ci\u003e\u003cu\u003eth\u003c/u\u003e\u003c/i\u003eahara amru All\u003cu\u003ea\u003c/u\u003ehi wahum k\u003cu\u003ea\u003c/u\u003erihoon\u003cb\u003ea\u003c/b\u003e"
    },
    {
        "BookCode":  "TLT",
        "SurahNumber":  "9",
        "AyahNumber":  "49",
        "Recitation":  "Alafasy_128kbps/009049",
        "Body":  "Waminhum man yaqoolu i\u003cu\u003eth\u003c/u\u003ean lee wal\u003cu\u003ea\u003c/u\u003e taftinnee al\u003cu\u003ea\u003c/u\u003e fee alfitnati saqa\u003cu\u003et\u003c/u\u003eoo wainna jahannama lamu\u003cu\u003eh\u003c/u\u003eee\u003cu\u003et\u003c/u\u003eatun bi\u003cb\u003ea\u003c/b\u003elk\u003cu\u003ea\u003c/u\u003efireen\u003cb\u003ea\u003c/b\u003e"
    },
    {
        "BookCode":  "TLT",
        "SurahNumber":  "9",
        "AyahNumber":  "5",
        "Recitation":  "Alafasy_128kbps/009005",
        "Body":  "Fai\u003cu\u003etha\u003c/u\u003e insalakha alashhuru al\u003cu\u003eh\u003c/u\u003eurumu fa\u003cb\u003eo\u003c/b\u003eqtuloo almushrikeena \u003cu\u003eh\u003c/u\u003eaythu wajadtumoohum wakhu\u003cu\u003eth\u003c/u\u003eoohum wa\u003cb\u003eo\u003c/b\u003e\u003cu\u003ehs\u003c/u\u003euroohum wa\u003cb\u003eo\u003c/b\u003eqAAudoo lahum kulla mar\u003cu\u003es\u003c/u\u003eadin fain t\u003cu\u003ea\u003c/u\u003eboo waaq\u003cu\u003ea\u003c/u\u003emoo a\u003cb\u003el\u003c/b\u003e\u003cu\u003ess\u003c/u\u003eal\u003cu\u003ea\u003c/u\u003eta wa\u003cu\u003ea\u003c/u\u003etawoo a\u003cb\u003el\u003c/b\u003ezzak\u003cu\u003ea\u003c/u\u003eta fakhalloo sabeelahum inna All\u003cu\u003ea\u003c/u\u003eha ghafoorun ra\u003cu\u003eh\u003c/u\u003eeem\u003cb\u003eun\u003c/b\u003e"
    },
    {
        "BookCode":  "TLT",
        "SurahNumber":  "9",
        "AyahNumber":  "50",
        "Recitation":  "Alafasy_128kbps/009050",
        "Body":  "In tu\u003cu\u003es\u003c/u\u003eibka \u003cu\u003eh\u003c/u\u003easanatun tasuhum wain tu\u003cu\u003es\u003c/u\u003eibka mu\u003cu\u003es\u003c/u\u003eeebatun yaqooloo qad akha\u003cu\u003eth\u003c/u\u003en\u003cu\u003ea\u003c/u\u003e amran\u003cu\u003ea\u003c/u\u003e min qablu wayatawallaw wahum fari\u003cu\u003eh\u003c/u\u003eoon\u003cb\u003ea\u003c/b\u003e"
    },
    {
        "BookCode":  "TLT",
        "SurahNumber":  "9",
        "AyahNumber":  "51",
        "Recitation":  "Alafasy_128kbps/009051",
        "Body":  "Qul lan yu\u003cu\u003es\u003c/u\u003eeeban\u003cu\u003ea\u003c/u\u003e ill\u003cu\u003ea\u003c/u\u003e m\u003cu\u003ea\u003c/u\u003e kataba All\u003cu\u003ea\u003c/u\u003ehu lan\u003cu\u003ea\u003c/u\u003e huwa mawl\u003cu\u003ea\u003c/u\u003en\u003cu\u003ea\u003c/u\u003e waAAal\u003cu\u003ea\u003c/u\u003e All\u003cu\u003ea\u003c/u\u003ehi falyatawakkali almuminoon\u003cb\u003ea\u003c/b\u003e"
    },
    {
        "BookCode":  "TLT",
        "SurahNumber":  "9",
        "AyahNumber":  "52",
        "Recitation":  "Alafasy_128kbps/009052",
        "Body":  "Qul hal tarabba\u003cu\u003es\u003c/u\u003eoona bin\u003cu\u003ea\u003c/u\u003e ill\u003cu\u003ea\u003c/u\u003e i\u003cu\u003eh\u003c/u\u003ed\u003cu\u003ea\u003c/u\u003e al\u003cu\u003eh\u003c/u\u003eusnayayni wana\u003cu\u003eh\u003c/u\u003enu natarabba\u003cu\u003es\u003c/u\u003eu bikum an yu\u003cu\u003es\u003c/u\u003eeebakumu All\u003cu\u003ea\u003c/u\u003ehu biAAa\u003cu\u003etha\u003c/u\u003ebin min AAindihi aw biaydeen\u003cu\u003ea\u003c/u\u003e fatarabba\u003cu\u003es\u003c/u\u003eoo inn\u003cu\u003ea\u003c/u\u003e maAAakum mutarabbi\u003cu\u003es\u003c/u\u003eoon\u003cb\u003ea\u003c/b\u003e"
    },
    {
        "BookCode":  "TLT",
        "SurahNumber":  "9",
        "AyahNumber":  "53",
        "Recitation":  "Alafasy_128kbps/009053",
        "Body":  "Qul anfiqoo \u003cu\u003et\u003c/u\u003eawAAan aw karhan lan yutaqabbala minkum innakum kuntum qawman f\u003cu\u003ea\u003c/u\u003esiqeen\u003cb\u003ea\u003c/b\u003e"
    },
    {
        "BookCode":  "TLT",
        "SurahNumber":  "9",
        "AyahNumber":  "54",
        "Recitation":  "Alafasy_128kbps/009054",
        "Body":  "Wam\u003cu\u003ea\u003c/u\u003e manaAAahum an tuqbala minhum nafaq\u003cu\u003ea\u003c/u\u003etuhum ill\u003cu\u003ea\u003c/u\u003e annahum kafaroo bi\u003cb\u003eA\u003c/b\u003ell\u003cu\u003ea\u003c/u\u003ehi wabirasoolihi wal\u003cu\u003ea\u003c/u\u003e yatoona a\u003cb\u003el\u003c/b\u003e\u003cu\u003ess\u003c/u\u003eal\u003cu\u003ea\u003c/u\u003eta ill\u003cu\u003ea\u003c/u\u003e wahum kus\u003cu\u003ea\u003c/u\u003el\u003cu\u003ea\u003c/u\u003e wal\u003cu\u003ea\u003c/u\u003e yunfiqoona ill\u003cu\u003ea\u003c/u\u003e wahum k\u003cu\u003ea\u003c/u\u003erihoon\u003cb\u003ea\u003c/b\u003e"
    },
    {
        "BookCode":  "TLT",
        "SurahNumber":  "9",
        "AyahNumber":  "55",
        "Recitation":  "Alafasy_128kbps/009055",
        "Body":  "Fal\u003cu\u003ea\u003c/u\u003e tuAAjibka amw\u003cu\u003ea\u003c/u\u003eluhum wal\u003cu\u003ea\u003c/u\u003e awl\u003cu\u003ea\u003c/u\u003eduhum innam\u003cu\u003ea\u003c/u\u003e yureedu All\u003cu\u003ea\u003c/u\u003ehu liyuAAa\u003cu\u003ethth\u003c/u\u003eibahum bih\u003cu\u003ea\u003c/u\u003e fee al\u003cu\u003eh\u003c/u\u003eay\u003cu\u003ea\u003c/u\u003eti a\u003cb\u003el\u003c/b\u003edduny\u003cu\u003ea\u003c/u\u003e watazhaqa anfusuhum wahum k\u003cu\u003ea\u003c/u\u003efiroon\u003cb\u003ea\u003c/b\u003e"
    },
    {
        "BookCode":  "TLT",
        "SurahNumber":  "9",
        "AyahNumber":  "56",
        "Recitation":  "Alafasy_128kbps/009056",
        "Body":  "Waya\u003cu\u003eh\u003c/u\u003elifoona bi\u003cb\u003eA\u003c/b\u003ell\u003cu\u003ea\u003c/u\u003ehi innahum laminkum wam\u003cu\u003ea\u003c/u\u003e hum minkum wal\u003cu\u003ea\u003c/u\u003ekinnahum qawmun yafraqoon\u003cb\u003ea\u003c/b\u003e"
    },
    {
        "BookCode":  "TLT",
        "SurahNumber":  "9",
        "AyahNumber":  "57",
        "Recitation":  "Alafasy_128kbps/009057",
        "Body":  "Law yajidoona maljaan aw magh\u003cu\u003ea\u003c/u\u003er\u003cu\u003ea\u003c/u\u003etin aw muddakhalan lawallaw ilayhi wahum yajma\u003cu\u003eh\u003c/u\u003eoon\u003cb\u003ea\u003c/b\u003e"
    },
    {
        "BookCode":  "TLT",
        "SurahNumber":  "9",
        "AyahNumber":  "58",
        "Recitation":  "Alafasy_128kbps/009058",
        "Body":  "Waminhum man yalmizuka fee a\u003cb\u003el\u003c/b\u003e\u003cu\u003ess\u003c/u\u003eadaq\u003cu\u003ea\u003c/u\u003eti fain oAA\u003cu\u003et\u003c/u\u003eoo minh\u003cu\u003ea\u003c/u\u003e ra\u003cu\u003ed\u003c/u\u003eoo wain lam yuAA\u003cu\u003et\u003c/u\u003eaw minh\u003cu\u003ea\u003c/u\u003e i\u003cu\u003etha\u003c/u\u003e hum yaskha\u003cu\u003et\u003c/u\u003eoon\u003cb\u003ea\u003c/b\u003e"
    },
    {
        "BookCode":  "TLT",
        "SurahNumber":  "9",
        "AyahNumber":  "59",
        "Recitation":  "Alafasy_128kbps/009059",
        "Body":  "Walaw annahum ra\u003cu\u003ed\u003c/u\u003eoo m\u003cu\u003ea\u003c/u\u003e \u003cu\u003ea\u003c/u\u003et\u003cu\u003ea\u003c/u\u003ehumu All\u003cu\u003ea\u003c/u\u003ehu warasooluhu waq\u003cu\u003ea\u003c/u\u003eloo \u003cu\u003eh\u003c/u\u003easbun\u003cu\u003ea\u003c/u\u003e All\u003cu\u003ea\u003c/u\u003ehu sayuteen\u003cu\u003ea\u003c/u\u003e All\u003cu\u003ea\u003c/u\u003ehu min fa\u003cu\u003ed\u003c/u\u003elihi warasooluhu inn\u003cu\u003ea\u003c/u\u003e il\u003cu\u003ea\u003c/u\u003e All\u003cu\u003ea\u003c/u\u003ehi r\u003cu\u003ea\u003c/u\u003eghiboon\u003cb\u003ea\u003c/b\u003e"
    },
    {
        "BookCode":  "TLT",
        "SurahNumber":  "9",
        "AyahNumber":  "6",
        "Recitation":  "Alafasy_128kbps/009006",
        "Body":  "Wain a\u003cu\u003eh\u003c/u\u003eadun mina almushrikeena istaj\u003cu\u003ea\u003c/u\u003eraka faajirhu \u003cu\u003eh\u003c/u\u003eatt\u003cu\u003ea\u003c/u\u003e yasmaAAa kal\u003cu\u003ea\u003c/u\u003ema All\u003cu\u003ea\u003c/u\u003ehi thumma ablighhu mamanahu \u003cu\u003etha\u003c/u\u003elika biannahum qawmun l\u003cu\u003ea\u003c/u\u003e yaAAlamoon\u003cb\u003ea\u003c/b\u003e"
    },
    {
        "BookCode":  "TLT",
        "SurahNumber":  "9",
        "AyahNumber":  "60",
        "Recitation":  "Alafasy_128kbps/009060",
        "Body":  "Innam\u003cu\u003ea\u003c/u\u003e a\u003cb\u003el\u003c/b\u003e\u003cu\u003ess\u003c/u\u003eadaq\u003cu\u003ea\u003c/u\u003etu lilfuqar\u003cu\u003ea\u003c/u\u003ei wa\u003cb\u003ea\u003c/b\u003elmas\u003cu\u003ea\u003c/u\u003ekeeni wa\u003cb\u003ea\u003c/b\u003elAA\u003cu\u003ea\u003c/u\u003emileena AAalayh\u003cu\u003ea\u003c/u\u003e wa\u003cb\u003ea\u003c/b\u003elmuallafati quloobuhum wafee a\u003cb\u003el\u003c/b\u003erriq\u003cu\u003ea\u003c/u\u003ebi wa\u003cb\u003ea\u003c/b\u003elgh\u003cu\u003ea\u003c/u\u003erimeena wafee sabeeli All\u003cu\u003ea\u003c/u\u003ehi wa\u003cb\u003ei\u003c/b\u003ebni a\u003cb\u003el\u003c/b\u003essabeeli faree\u003cu\u003ed\u003c/u\u003eatan mina All\u003cu\u003ea\u003c/u\u003ehi wa\u003cb\u003eA\u003c/b\u003ell\u003cu\u003ea\u003c/u\u003ehu AAaleemun \u003cu\u003eh\u003c/u\u003eakeemun"
    },
    {
        "BookCode":  "TLT",
        "SurahNumber":  "9",
        "AyahNumber":  "61",
        "Recitation":  "Alafasy_128kbps/009061",
        "Body":  "Waminhumu alla\u003cu\u003eth\u003c/u\u003eeena yu\u003cu\u003eth\u003c/u\u003eoona a\u003cb\u003el\u003c/b\u003ennabiyya wayaqooloona huwa o\u003cu\u003eth\u003c/u\u003eunun qul o\u003cu\u003eth\u003c/u\u003eunu khayrin lakum yuminu bi\u003cb\u003eA\u003c/b\u003ell\u003cu\u003ea\u003c/u\u003ehi wayuminu lilmumineena wara\u003cu\u003eh\u003c/u\u003ematun lilla\u003cu\u003eth\u003c/u\u003eeena \u003cu\u003ea\u003c/u\u003emanoo minkum wa\u003cb\u003ea\u003c/b\u003ella\u003cu\u003eth\u003c/u\u003eeena yu\u003cu\u003eth\u003c/u\u003eoona rasoola All\u003cu\u003ea\u003c/u\u003ehi lahum AAa\u003cu\u003etha\u003c/u\u003ebun aleem\u003cb\u003eun\u003c/b\u003e"
    },
    {
        "BookCode":  "TLT",
        "SurahNumber":  "9",
        "AyahNumber":  "62",
        "Recitation":  "Alafasy_128kbps/009062",
        "Body":  "Ya\u003cu\u003eh\u003c/u\u003elifoona bi\u003cb\u003eA\u003c/b\u003ell\u003cu\u003ea\u003c/u\u003ehi lakum liyur\u003cu\u003ed\u003c/u\u003eookum wa\u003cb\u003eA\u003c/b\u003ell\u003cu\u003ea\u003c/u\u003ehu warasooluhu a\u003cu\u003eh\u003c/u\u003eaqqu an yur\u003cu\u003ed\u003c/u\u003eoohu in k\u003cu\u003ea\u003c/u\u003enoo mumineen\u003cb\u003ea\u003c/b\u003e"
    },
    {
        "BookCode":  "TLT",
        "SurahNumber":  "9",
        "AyahNumber":  "63",
        "Recitation":  "Alafasy_128kbps/009063",
        "Body":  "Alam yaAAlamoo annahu man yu\u003cu\u003eha\u003c/u\u003edidi All\u003cu\u003ea\u003c/u\u003eha warasoolahu faanna lahu n\u003cu\u003ea\u003c/u\u003era jahannama kh\u003cu\u003ea\u003c/u\u003elidan feeh\u003cu\u003ea\u003c/u\u003e \u003cu\u003etha\u003c/u\u003elika alkhizyu alAAa\u003ci\u003e\u003cu\u003eth\u003c/u\u003e\u003c/i\u003eeem\u003cb\u003eu\u003c/b\u003e"
    },
    {
        "BookCode":  "TLT",
        "SurahNumber":  "9",
        "AyahNumber":  "64",
        "Recitation":  "Alafasy_128kbps/009064",
        "Body":  "Ya\u003cu\u003ehth\u003c/u\u003earu almun\u003cu\u003ea\u003c/u\u003efiqoona an tunazzala AAalayhim sooratun tunabbiohum bim\u003cu\u003ea\u003c/u\u003e fee quloobihim quli istahzioo inna All\u003cu\u003ea\u003c/u\u003eha mukhrijun m\u003cu\u003ea\u003c/u\u003e ta\u003cu\u003ehth\u003c/u\u003earoon\u003cb\u003ea\u003c/b\u003e"
    },
    {
        "BookCode":  "TLT",
        "SurahNumber":  "9",
        "AyahNumber":  "65",
        "Recitation":  "Alafasy_128kbps/009065",
        "Body":  "Walain saaltahum layaqoolunna innam\u003cu\u003ea\u003c/u\u003e kunn\u003cu\u003ea\u003c/u\u003e nakhoo\u003cu\u003ed\u003c/u\u003eu wanalAAabu qul abi\u003cb\u003eA\u003c/b\u003ell\u003cu\u003ea\u003c/u\u003ehi wa\u003cu\u003ea\u003c/u\u003ey\u003cu\u003ea\u003c/u\u003etihi warasoolihi kuntum tastahzioon\u003cb\u003ea\u003c/b\u003e"
    },
    {
        "BookCode":  "TLT",
        "SurahNumber":  "9",
        "AyahNumber":  "66",
        "Recitation":  "Alafasy_128kbps/009066",
        "Body":  "L\u003cu\u003ea\u003c/u\u003e taAAta\u003cu\u003eth\u003c/u\u003eiroo qad kafartum baAAda eem\u003cu\u003ea\u003c/u\u003enikum in naAAfu AAan \u003cu\u003eta\u003c/u\u003eifatin minkum nuAAa\u003cu\u003ethth\u003c/u\u003eib \u003cu\u003eta\u003c/u\u003eifatan biannahum k\u003cu\u003ea\u003c/u\u003enoo mujrimeen\u003cb\u003ea\u003c/b\u003e"
    },
    {
        "BookCode":  "TLT",
        "SurahNumber":  "9",
        "AyahNumber":  "67",
        "Recitation":  "Alafasy_128kbps/009067",
        "Body":  "Almun\u003cu\u003ea\u003c/u\u003efiqoona wa\u003cb\u003ea\u003c/b\u003elmun\u003cu\u003ea\u003c/u\u003efiq\u003cu\u003ea\u003c/u\u003etu baAA\u003cu\u003ed\u003c/u\u003euhum min baAA\u003cu\u003ed\u003c/u\u003ein yamuroona bi\u003cb\u003ea\u003c/b\u003elmunkari wayanhawna AAani almaAAroofi wayaqbi\u003cu\u003ed\u003c/u\u003eoona aydiyahum nasoo All\u003cu\u003ea\u003c/u\u003eha fanasiyahum inna almun\u003cu\u003ea\u003c/u\u003efiqeena humu alf\u003cu\u003ea\u003c/u\u003esiqoon\u003cb\u003ea\u003c/b\u003e"
    },
    {
        "BookCode":  "TLT",
        "SurahNumber":  "9",
        "AyahNumber":  "68",
        "Recitation":  "Alafasy_128kbps/009068",
        "Body":  "WaAAada All\u003cu\u003ea\u003c/u\u003ehu almun\u003cu\u003ea\u003c/u\u003efiqeena wa\u003cb\u003ea\u003c/b\u003elmun\u003cu\u003ea\u003c/u\u003efiq\u003cu\u003ea\u003c/u\u003eti wa\u003cb\u003ea\u003c/b\u003elkuff\u003cu\u003ea\u003c/u\u003era n\u003cu\u003ea\u003c/u\u003era jahannama kh\u003cu\u003ea\u003c/u\u003elideena feeh\u003cu\u003ea\u003c/u\u003e hiya \u003cu\u003eh\u003c/u\u003easbuhum walaAAanahumu All\u003cu\u003ea\u003c/u\u003ehu walahum AAa\u003cu\u003etha\u003c/u\u003ebun muqeem\u003cb\u003eun\u003c/b\u003e"
    },
    {
        "BookCode":  "TLT",
        "SurahNumber":  "9",
        "AyahNumber":  "69",
        "Recitation":  "Alafasy_128kbps/009069",
        "Body":  "Ka\u003cb\u003ea\u003c/b\u003ella\u003cu\u003eth\u003c/u\u003eeena min qablikum k\u003cu\u003ea\u003c/u\u003enoo ashadda minkum quwwatan waakthara amw\u003cu\u003ea\u003c/u\u003elan waawl\u003cu\u003ea\u003c/u\u003edan fa\u003cb\u003ei\u003c/b\u003estamtaAAoo bikhal\u003cu\u003ea\u003c/u\u003eqihim fa\u003cb\u003ei\u003c/b\u003estamtaAAtum bikhal\u003cu\u003ea\u003c/u\u003eqikum kam\u003cu\u003ea\u003c/u\u003e istamtaAAa alla\u003cu\u003eth\u003c/u\u003eeena min qablikum bikhal\u003cu\u003ea\u003c/u\u003eqihim wakhu\u003cu\u003ed\u003c/u\u003etum ka\u003cb\u003ea\u003c/b\u003ella\u003cu\u003eth\u003c/u\u003eee kh\u003cu\u003ead\u003c/u\u003eoo ol\u003cu\u003ea\u003c/u\u003eika \u003cu\u003eh\u003c/u\u003eabi\u003cu\u003et\u003c/u\u003eat aAAm\u003cu\u003ea\u003c/u\u003eluhum fee a\u003cb\u003el\u003c/b\u003edduny\u003cu\u003ea\u003c/u\u003e wa\u003cb\u003ea\u003c/b\u003el\u003cu\u003ea\u003c/u\u003ekhirati waol\u003cu\u003ea\u003c/u\u003eika humu alkh\u003cu\u003ea\u003c/u\u003esiroon\u003cb\u003ea\u003c/b\u003e"
    },
    {
        "BookCode":  "TLT",
        "SurahNumber":  "9",
        "AyahNumber":  "7",
        "Recitation":  "Alafasy_128kbps/009007",
        "Body":  "Kayfa yakoonu lilmushrikeena AAahdun AAinda All\u003cu\u003ea\u003c/u\u003ehi waAAinda rasoolihi ill\u003cu\u003ea\u003c/u\u003e alla\u003cu\u003eth\u003c/u\u003eeena AA\u003cu\u003ea\u003c/u\u003ehadtum AAinda almasjidi al\u003cu\u003eh\u003c/u\u003ear\u003cu\u003ea\u003c/u\u003emi fam\u003cu\u003ea\u003c/u\u003e istaq\u003cu\u003ea\u003c/u\u003emoo lakum fa\u003cb\u003ei\u003c/b\u003estaqeemoo lahum inna All\u003cu\u003ea\u003c/u\u003eha yu\u003cu\u003eh\u003c/u\u003eibbu almuttaqeen\u003cb\u003ea\u003c/b\u003e"
    },
    {
        "BookCode":  "TLT",
        "SurahNumber":  "9",
        "AyahNumber":  "70",
        "Recitation":  "Alafasy_128kbps/009070",
        "Body":  "Alam yatihim nabao alla\u003cu\u003eth\u003c/u\u003eeena min qablihim qawmi noo\u003cu\u003eh\u003c/u\u003ein waAA\u003cu\u003ea\u003c/u\u003edin wathamooda waqawmi ibr\u003cu\u003ea\u003c/u\u003eheema waa\u003cu\u003es\u003c/u\u003e\u003cu\u003eha\u003c/u\u003ebi madyana wa\u003cb\u003ea\u003c/b\u003elmutafik\u003cu\u003ea\u003c/u\u003eti atathum rusuluhum bi\u003cb\u003ea\u003c/b\u003elbayyin\u003cu\u003ea\u003c/u\u003eti fam\u003cu\u003ea\u003c/u\u003e k\u003cu\u003ea\u003c/u\u003ena All\u003cu\u003ea\u003c/u\u003ehu liya\u003ci\u003e\u003cu\u003eth\u003c/u\u003e\u003c/i\u003elimahum wal\u003cu\u003ea\u003c/u\u003ekin k\u003cu\u003ea\u003c/u\u003enoo anfusahum ya\u003ci\u003e\u003cu\u003eth\u003c/u\u003e\u003c/i\u003elimoon\u003cb\u003ea\u003c/b\u003e"
    },
    {
        "BookCode":  "TLT",
        "SurahNumber":  "9",
        "AyahNumber":  "71",
        "Recitation":  "Alafasy_128kbps/009071",
        "Body":  "Wa\u003cb\u003ea\u003c/b\u003elmuminoona wa\u003cb\u003ea\u003c/b\u003elmumin\u003cu\u003ea\u003c/u\u003etu baAA\u003cu\u003ed\u003c/u\u003euhum awliy\u003cu\u003ea\u003c/u\u003eo baAA\u003cu\u003ed\u003c/u\u003ein yamuroona bi\u003cb\u003ea\u003c/b\u003elmaAAroofi wayanhawna AAani almunkari wayuqeemoona a\u003cb\u003el\u003c/b\u003e\u003cu\u003ess\u003c/u\u003eal\u003cu\u003ea\u003c/u\u003eta wayutoona a\u003cb\u003el\u003c/b\u003ezzak\u003cu\u003ea\u003c/u\u003eta wayu\u003cu\u003et\u003c/u\u003eeeAAoona All\u003cu\u003ea\u003c/u\u003eha warasoolahu ol\u003cu\u003ea\u003c/u\u003eika sayar\u003cu\u003eh\u003c/u\u003eamuhumu All\u003cu\u003ea\u003c/u\u003ehu inna All\u003cu\u003ea\u003c/u\u003eha AAazeezun \u003cu\u003eh\u003c/u\u003eakeem\u003cb\u003eun\u003c/b\u003e"
    },
    {
        "BookCode":  "TLT",
        "SurahNumber":  "9",
        "AyahNumber":  "72",
        "Recitation":  "Alafasy_128kbps/009072",
        "Body":  "WaAAada All\u003cu\u003ea\u003c/u\u003ehu almumineena wa\u003cb\u003ea\u003c/b\u003elmumin\u003cu\u003ea\u003c/u\u003eti jann\u003cu\u003ea\u003c/u\u003etin tajree min ta\u003cu\u003eh\u003c/u\u003etih\u003cu\u003ea\u003c/u\u003e alanh\u003cu\u003ea\u003c/u\u003eru kh\u003cu\u003ea\u003c/u\u003elideena feeh\u003cu\u003ea\u003c/u\u003e wamas\u003cu\u003ea\u003c/u\u003ekina \u003cu\u003et\u003c/u\u003eayyibatan fee jann\u003cu\u003ea\u003c/u\u003eti AAadnin wari\u003cu\u003ed\u003c/u\u003ew\u003cu\u003ea\u003c/u\u003enun mina All\u003cu\u003ea\u003c/u\u003ehi akbaru \u003cu\u003etha\u003c/u\u003elika huwa alfawzu alAAa\u003ci\u003e\u003cu\u003eth\u003c/u\u003e\u003c/i\u003eeem\u003cb\u003eu\u003c/b\u003e"
    },
    {
        "BookCode":  "TLT",
        "SurahNumber":  "9",
        "AyahNumber":  "73",
        "Recitation":  "Alafasy_128kbps/009073",
        "Body":  "Y\u003cu\u003ea\u003c/u\u003e ayyuh\u003cu\u003ea\u003c/u\u003e a\u003cb\u003el\u003c/b\u003ennabiyyu j\u003cu\u003ea\u003c/u\u003ehidi alkuff\u003cu\u003ea\u003c/u\u003era wa\u003cb\u003ea\u003c/b\u003elmun\u003cu\u003ea\u003c/u\u003efiqeena wa\u003cb\u003eo\u003c/b\u003eghlu\u003ci\u003e\u003cu\u003eth\u003c/u\u003e\u003c/i\u003e AAalayhim wamaw\u003cu\u003ea\u003c/u\u003ehum jahannamu wabisa alma\u003cu\u003es\u003c/u\u003eeer\u003cb\u003eu\u003c/b\u003e"
    },
    {
        "BookCode":  "TLT",
        "SurahNumber":  "9",
        "AyahNumber":  "74",
        "Recitation":  "Alafasy_128kbps/009074",
        "Body":  "Ya\u003cu\u003eh\u003c/u\u003elifoona bi\u003cb\u003eA\u003c/b\u003ell\u003cu\u003ea\u003c/u\u003ehi m\u003cu\u003ea\u003c/u\u003e q\u003cu\u003ea\u003c/u\u003eloo walaqad q\u003cu\u003ea\u003c/u\u003eloo kalimata alkufri wakafaroo baAAda isl\u003cu\u003ea\u003c/u\u003emihim wahammoo bim\u003cu\u003ea\u003c/u\u003e lam yan\u003cu\u003ea\u003c/u\u003eloo wam\u003cu\u003ea\u003c/u\u003e naqamoo ill\u003cu\u003ea\u003c/u\u003e an aghn\u003cu\u003ea\u003c/u\u003ehumu All\u003cu\u003ea\u003c/u\u003ehu warasooluhu min fa\u003cu\u003ed\u003c/u\u003elihi fain yatooboo yaku khayran lahum wain yatawallaw yuAAa\u003cu\u003ethth\u003c/u\u003eibhumu All\u003cu\u003ea\u003c/u\u003ehu AAa\u003cu\u003etha\u003c/u\u003eban aleeman fee a\u003cb\u003el\u003c/b\u003edduny\u003cu\u003ea\u003c/u\u003e wa\u003cb\u003ea\u003c/b\u003el\u003cu\u003ea\u003c/u\u003ekhirati wam\u003cu\u003ea\u003c/u\u003e lahum fee alar\u003cu\u003ed\u003c/u\u003ei min waliyyin wal\u003cu\u003ea\u003c/u\u003e na\u003cu\u003es\u003c/u\u003eeer\u003cb\u003ein\u003c/b\u003e"
    },
    {
        "BookCode":  "TLT",
        "SurahNumber":  "9",
        "AyahNumber":  "75",
        "Recitation":  "Alafasy_128kbps/009075",
        "Body":  "Waminhum man AA\u003cu\u003ea\u003c/u\u003ehada All\u003cu\u003ea\u003c/u\u003eha lain \u003cu\u003ea\u003c/u\u003et\u003cu\u003ea\u003c/u\u003en\u003cu\u003ea\u003c/u\u003e min fa\u003cu\u003ed\u003c/u\u003elihi lana\u003cu\u003ess\u003c/u\u003eaddaqanna walanakoonanna mina a\u003cb\u003el\u003c/b\u003e\u003cu\u003essa\u003c/u\u003eli\u003cu\u003eh\u003c/u\u003eeen\u003cb\u003ea\u003c/b\u003e"
    },
    {
        "BookCode":  "TLT",
        "SurahNumber":  "9",
        "AyahNumber":  "76",
        "Recitation":  "Alafasy_128kbps/009076",
        "Body":  "Falamm\u003cu\u003ea\u003c/u\u003e \u003cu\u003ea\u003c/u\u003et\u003cu\u003ea\u003c/u\u003ehum min fa\u003cu\u003ed\u003c/u\u003elihi bakhiloo bihi watawallaw wahum muAAri\u003cu\u003ed\u003c/u\u003eoon\u003cb\u003ea\u003c/b\u003e"
    },
    {
        "BookCode":  "TLT",
        "SurahNumber":  "9",
        "AyahNumber":  "77",
        "Recitation":  "Alafasy_128kbps/009077",
        "Body":  "FaaAAqabahum nif\u003cu\u003ea\u003c/u\u003eqan fee quloobihim il\u003cu\u003ea\u003c/u\u003e yawmi yalqawnahu bim\u003cu\u003ea\u003c/u\u003e akhlafoo All\u003cu\u003ea\u003c/u\u003eha m\u003cu\u003ea\u003c/u\u003e waAAadoohu wabim\u003cu\u003ea\u003c/u\u003e k\u003cu\u003ea\u003c/u\u003enoo yak\u003cu\u003eth\u003c/u\u003eiboon\u003cb\u003ea\u003c/b\u003e"
    },
    {
        "BookCode":  "TLT",
        "SurahNumber":  "9",
        "AyahNumber":  "78",
        "Recitation":  "Alafasy_128kbps/009078",
        "Body":  "Alam yaAAlamoo anna All\u003cu\u003ea\u003c/u\u003eha yaAAlamu sirrahum wanajw\u003cu\u003ea\u003c/u\u003ehum waanna All\u003cu\u003ea\u003c/u\u003eha AAall\u003cu\u003ea\u003c/u\u003emu alghuyoob\u003cb\u003ei\u003c/b\u003e"
    },
    {
        "BookCode":  "TLT",
        "SurahNumber":  "9",
        "AyahNumber":  "79",
        "Recitation":  "Alafasy_128kbps/009079",
        "Body":  "Alla\u003cu\u003eth\u003c/u\u003eeena yalmizoona almu\u003cu\u003ett\u003c/u\u003eawwiAAeena mina almumineena fee a\u003cb\u003el\u003c/b\u003e\u003cu\u003ess\u003c/u\u003eadaq\u003cu\u003ea\u003c/u\u003eti wa\u003cb\u003ea\u003c/b\u003ella\u003cu\u003eth\u003c/u\u003eeena l\u003cu\u003ea\u003c/u\u003e yajidoona ill\u003cu\u003ea\u003c/u\u003e juhdahum fayaskharoona minhum sakhira All\u003cu\u003ea\u003c/u\u003ehu minhum walahum AAa\u003cu\u003etha\u003c/u\u003ebun aleem\u003cb\u003eun\u003c/b\u003e"
    },
    {
        "BookCode":  "TLT",
        "SurahNumber":  "9",
        "AyahNumber":  "8",
        "Recitation":  "Alafasy_128kbps/009008",
        "Body":  "Kayfa wain ya\u003ci\u003e\u003cu\u003eth\u003c/u\u003e\u003c/i\u003eharoo AAalaykum l\u003cu\u003ea\u003c/u\u003e yarquboo feekum illan wal\u003cu\u003ea\u003c/u\u003e \u003cu\u003eth\u003c/u\u003eimmatan yur\u003cu\u003ed\u003c/u\u003eoonakum biafw\u003cu\u003ea\u003c/u\u003ehihim watab\u003cu\u003ea\u003c/u\u003e quloobuhum waaktharuhum f\u003cu\u003ea\u003c/u\u003esiqoon\u003cb\u003ea\u003c/b\u003e"
    },
    {
        "BookCode":  "TLT",
        "SurahNumber":  "9",
        "AyahNumber":  "80",
        "Recitation":  "Alafasy_128kbps/009080",
        "Body":  "Istaghfir lahum aw l\u003cu\u003ea\u003c/u\u003e tastaghfir lahum in tastaghfir lahum sabAAeena marratan falan yaghfira All\u003cu\u003ea\u003c/u\u003ehu lahum \u003cu\u003etha\u003c/u\u003elika biannahum kafaroo bi\u003cb\u003eA\u003c/b\u003ell\u003cu\u003ea\u003c/u\u003ehi warasoolihi wa\u003cb\u003eA\u003c/b\u003ell\u003cu\u003ea\u003c/u\u003ehu l\u003cu\u003ea\u003c/u\u003e yahdee alqawma alf\u003cu\u003ea\u003c/u\u003esiqeen\u003cb\u003ea\u003c/b\u003e"
    },
    {
        "BookCode":  "TLT",
        "SurahNumber":  "9",
        "AyahNumber":  "81",
        "Recitation":  "Alafasy_128kbps/009081",
        "Body":  "Fari\u003cu\u003eh\u003c/u\u003ea almukhallafoona bimaqAAadihim khil\u003cu\u003ea\u003c/u\u003efa rasooli All\u003cu\u003ea\u003c/u\u003ehi wakarihoo an yuj\u003cu\u003ea\u003c/u\u003ehidoo biamw\u003cu\u003ea\u003c/u\u003elihim waanfusihim fee sabeeli All\u003cu\u003ea\u003c/u\u003ehi waq\u003cu\u003ea\u003c/u\u003eloo l\u003cu\u003ea\u003c/u\u003e tanfiroo fee al\u003cu\u003eh\u003c/u\u003earri qul n\u003cu\u003ea\u003c/u\u003eru jahannama ashaddu \u003cu\u003eh\u003c/u\u003earran law k\u003cu\u003ea\u003c/u\u003enoo yafqahoon\u003cb\u003ea\u003c/b\u003e"
    },
    {
        "BookCode":  "TLT",
        "SurahNumber":  "9",
        "AyahNumber":  "82",
        "Recitation":  "Alafasy_128kbps/009082",
        "Body":  "Falya\u003cu\u003edh\u003c/u\u003eakoo qaleelan walyabkoo katheeran jaz\u003cu\u003ea\u003c/u\u003ean bim\u003cu\u003ea\u003c/u\u003e k\u003cu\u003ea\u003c/u\u003enoo yaksiboon\u003cb\u003ea\u003c/b\u003e"
    },
    {
        "BookCode":  "TLT",
        "SurahNumber":  "9",
        "AyahNumber":  "83",
        "Recitation":  "Alafasy_128kbps/009083",
        "Body":  "Fain rajaAAaka All\u003cu\u003ea\u003c/u\u003ehu il\u003cu\u003ea\u003c/u\u003e \u003cu\u003eta\u003c/u\u003eifatin minhum fa\u003cb\u003ei\u003c/b\u003esta\u003cu\u003eth\u003c/u\u003eanooka lilkhurooji faqul lan takhrujoo maAAiya abadan walan tuq\u003cu\u003ea\u003c/u\u003etiloo maAAiya AAaduwwan innakum ra\u003cu\u003ed\u003c/u\u003eeetum bi\u003cb\u003ea\u003c/b\u003elquAAoodi awwala marratin fa\u003cb\u003eo\u003c/b\u003eqAAudoo maAAa alkh\u003cu\u003ea\u003c/u\u003elifeen\u003cb\u003ea\u003c/b\u003e"
    },
    {
        "BookCode":  "TLT",
        "SurahNumber":  "9",
        "AyahNumber":  "84",
        "Recitation":  "Alafasy_128kbps/009084",
        "Body":  "Wal\u003cu\u003ea\u003c/u\u003e tu\u003cu\u003es\u003c/u\u003ealli AAal\u003cu\u003ea\u003c/u\u003e a\u003cu\u003eh\u003c/u\u003eadin minhum m\u003cu\u003ea\u003c/u\u003eta abadan wal\u003cu\u003ea\u003c/u\u003e taqum AAal\u003cu\u003ea\u003c/u\u003e qabrihi innahum kafaroo bi\u003cb\u003eA\u003c/b\u003ell\u003cu\u003ea\u003c/u\u003ehi warasoolihi wam\u003cu\u003ea\u003c/u\u003etoo wahum f\u003cu\u003ea\u003c/u\u003esiqoon\u003cb\u003ea\u003c/b\u003e"
    },
    {
        "BookCode":  "TLT",
        "SurahNumber":  "9",
        "AyahNumber":  "85",
        "Recitation":  "Alafasy_128kbps/009085",
        "Body":  "Wal\u003cu\u003ea\u003c/u\u003e tuAAjibka amw\u003cu\u003ea\u003c/u\u003eluhum waawl\u003cu\u003ea\u003c/u\u003eduhum innam\u003cu\u003ea\u003c/u\u003e yureedu All\u003cu\u003ea\u003c/u\u003ehu an yuAAa\u003cu\u003ethth\u003c/u\u003eibahum bih\u003cu\u003ea\u003c/u\u003e fee a\u003cb\u003el\u003c/b\u003edduny\u003cu\u003ea\u003c/u\u003e watazhaqa anfusuhum wahum k\u003cu\u003ea\u003c/u\u003efiroon\u003cb\u003ea\u003c/b\u003e"
    },
    {
        "BookCode":  "TLT",
        "SurahNumber":  "9",
        "AyahNumber":  "86",
        "Recitation":  "Alafasy_128kbps/009086",
        "Body":  "Wai\u003cu\u003etha\u003c/u\u003e onzilat sooratun an \u003cu\u003ea\u003c/u\u003eminoo bi\u003cb\u003eA\u003c/b\u003ell\u003cu\u003ea\u003c/u\u003ehi waj\u003cu\u003ea\u003c/u\u003ehidoo maAAa rasoolihi ista\u003cu\u003eth\u003c/u\u003eanaka oloo a\u003cb\u003el\u003c/b\u003e\u003cu\u003ett\u003c/u\u003eawli minhum waq\u003cu\u003ea\u003c/u\u003eloo \u003cu\u003eth\u003c/u\u003earn\u003cu\u003ea\u003c/u\u003e nakun maAAa alq\u003cu\u003ea\u003c/u\u003eAAideen\u003cb\u003ea\u003c/b\u003e"
    },
    {
        "BookCode":  "TLT",
        "SurahNumber":  "9",
        "AyahNumber":  "87",
        "Recitation":  "Alafasy_128kbps/009087",
        "Body":  "Ra\u003cu\u003ed\u003c/u\u003eoo bian yakoonoo maAAa alkhaw\u003cu\u003ea\u003c/u\u003elifi wa\u003cu\u003et\u003c/u\u003eubiAAa AAal\u003cu\u003ea\u003c/u\u003e quloobihim fahum l\u003cu\u003ea\u003c/u\u003e yafqahoon\u003cb\u003ea\u003c/b\u003e"
    },
    {
        "BookCode":  "TLT",
        "SurahNumber":  "9",
        "AyahNumber":  "88",
        "Recitation":  "Alafasy_128kbps/009088",
        "Body":  "L\u003cu\u003ea\u003c/u\u003ekini a\u003cb\u003el\u003c/b\u003errasoolu wa\u003cb\u003ea\u003c/b\u003ella\u003cu\u003eth\u003c/u\u003eeena \u003cu\u003ea\u003c/u\u003emanoo maAAahu j\u003cu\u003ea\u003c/u\u003ehadoo biamw\u003cu\u003ea\u003c/u\u003elihim waanfusihim waol\u003cu\u003ea\u003c/u\u003eika lahumu alkhayr\u003cu\u003ea\u003c/u\u003etu waol\u003cu\u003ea\u003c/u\u003eika humu almufli\u003cu\u003eh\u003c/u\u003eoon\u003cb\u003ea\u003c/b\u003e"
    },
    {
        "BookCode":  "TLT",
        "SurahNumber":  "9",
        "AyahNumber":  "89",
        "Recitation":  "Alafasy_128kbps/009089",
        "Body":  "aAAadda All\u003cu\u003ea\u003c/u\u003ehu lahum jann\u003cu\u003ea\u003c/u\u003etin tajree min ta\u003cu\u003eh\u003c/u\u003etih\u003cu\u003ea\u003c/u\u003e alanh\u003cu\u003ea\u003c/u\u003eru kh\u003cu\u003ea\u003c/u\u003elideena feeh\u003cu\u003ea\u003c/u\u003e \u003cu\u003etha\u003c/u\u003elika alfawzu alAAa\u003ci\u003e\u003cu\u003eth\u003c/u\u003e\u003c/i\u003eeem\u003cb\u003eu\u003c/b\u003e"
    },
    {
        "BookCode":  "TLT",
        "SurahNumber":  "9",
        "AyahNumber":  "9",
        "Recitation":  "Alafasy_128kbps/009009",
        "Body":  "Ishtaraw bi\u003cu\u003ea\u003c/u\u003ey\u003cu\u003ea\u003c/u\u003eti All\u003cu\u003ea\u003c/u\u003ehi thamanan qaleelan fa\u003cu\u003es\u003c/u\u003eaddoo AAan sabeelihi innahum s\u003cu\u003ea\u003c/u\u003ea m\u003cu\u003ea\u003c/u\u003e k\u003cu\u003ea\u003c/u\u003enoo yaAAmaloon\u003cb\u003ea\u003c/b\u003e"
    },
    {
        "BookCode":  "TLT",
        "SurahNumber":  "9",
        "AyahNumber":  "90",
        "Recitation":  "Alafasy_128kbps/009090",
        "Body":  "Waj\u003cu\u003ea\u003c/u\u003ea almuAAa\u003cu\u003ethth\u003c/u\u003eiroona mina alaAAr\u003cu\u003ea\u003c/u\u003ebi liyu\u003cu\u003eth\u003c/u\u003eana lahum waqaAAada alla\u003cu\u003eth\u003c/u\u003eeena ka\u003cu\u003eth\u003c/u\u003eaboo All\u003cu\u003ea\u003c/u\u003eha warasoolahu sayu\u003cu\u003es\u003c/u\u003eeebu alla\u003cu\u003eth\u003c/u\u003eeena kafaroo minhum AAa\u003cu\u003etha\u003c/u\u003ebun aleem\u003cb\u003eun\u003c/b\u003e"
    },
    {
        "BookCode":  "TLT",
        "SurahNumber":  "9",
        "AyahNumber":  "91",
        "Recitation":  "Alafasy_128kbps/009091",
        "Body":  "Laysa AAal\u003cu\u003ea\u003c/u\u003e a\u003cb\u003el\u003c/b\u003e\u003cu\u003edd\u003c/u\u003euAAaf\u003cu\u003ea\u003c/u\u003ei wal\u003cu\u003ea\u003c/u\u003e AAal\u003cu\u003ea\u003c/u\u003e almar\u003cu\u003eda\u003c/u\u003e wal\u003cu\u003ea\u003c/u\u003e AAal\u003cu\u003ea\u003c/u\u003e alla\u003cu\u003eth\u003c/u\u003eeena l\u003cu\u003ea\u003c/u\u003e yajidoona m\u003cu\u003ea\u003c/u\u003e yunfiqoona \u003cu\u003eh\u003c/u\u003earajun i\u003cu\u003etha\u003c/u\u003e na\u003cu\u003es\u003c/u\u003ea\u003cu\u003eh\u003c/u\u003eoo lill\u003cu\u003ea\u003c/u\u003ehi warasoolihi m\u003cu\u003ea\u003c/u\u003e AAal\u003cu\u003ea\u003c/u\u003e almu\u003cu\u003eh\u003c/u\u003esineena min sabeelin wa\u003cb\u003eA\u003c/b\u003ell\u003cu\u003ea\u003c/u\u003ehu ghafoorun ra\u003cu\u003eh\u003c/u\u003eeem\u003cb\u003eun\u003c/b\u003e"
    },
    {
        "BookCode":  "TLT",
        "SurahNumber":  "9",
        "AyahNumber":  "92",
        "Recitation":  "Alafasy_128kbps/009092",
        "Body":  "Wal\u003cu\u003ea\u003c/u\u003e AAal\u003cu\u003ea\u003c/u\u003e alla\u003cu\u003eth\u003c/u\u003eeena i\u003cu\u003etha\u003c/u\u003e m\u003cu\u003ea\u003c/u\u003e atawka lita\u003cu\u003eh\u003c/u\u003emilahum qulta l\u003cu\u003ea\u003c/u\u003e ajidu m\u003cu\u003ea\u003c/u\u003e a\u003cu\u003eh\u003c/u\u003emilukum AAalayhi tawallaw waaAAyunuhum tafee\u003cu\u003ed\u003c/u\u003eu mina a\u003cb\u003el\u003c/b\u003eddamAAi \u003cu\u003eh\u003c/u\u003eazanan all\u003cu\u003ea\u003c/u\u003e yajidoo m\u003cu\u003ea\u003c/u\u003e yunfiqoon\u003cb\u003ea\u003c/b\u003e"
    },
    {
        "BookCode":  "TLT",
        "SurahNumber":  "9",
        "AyahNumber":  "93",
        "Recitation":  "Alafasy_128kbps/009093",
        "Body":  "Innam\u003cu\u003ea\u003c/u\u003e a\u003cb\u003el\u003c/b\u003essabeelu AAal\u003cu\u003ea\u003c/u\u003e alla\u003cu\u003eth\u003c/u\u003eeena yasta\u003cu\u003eth\u003c/u\u003einoonaka wahum aghniy\u003cu\u003ea\u003c/u\u003eo ra\u003cu\u003ed\u003c/u\u003eoo bian yakoonoo maAAa alkhaw\u003cu\u003ea\u003c/u\u003elifi wa\u003cu\u003et\u003c/u\u003eabaAAa All\u003cu\u003ea\u003c/u\u003ehu AAal\u003cu\u003ea\u003c/u\u003e quloobihim fahum l\u003cu\u003ea\u003c/u\u003e yaAAlamoon\u003cb\u003ea\u003c/b\u003e"
    },
    {
        "BookCode":  "TLT",
        "SurahNumber":  "9",
        "AyahNumber":  "94",
        "Recitation":  "Alafasy_128kbps/009094",
        "Body":  "YaAAta\u003cu\u003eth\u003c/u\u003eiroona ilaykum i\u003cu\u003etha\u003c/u\u003e rajaAAtum ilayhim qul l\u003cu\u003ea\u003c/u\u003e taAAta\u003cu\u003eth\u003c/u\u003eiroo lan numina lakum qad nabbaan\u003cu\u003ea\u003c/u\u003e All\u003cu\u003ea\u003c/u\u003ehu min akhb\u003cu\u003ea\u003c/u\u003erikum wasayar\u003cu\u003ea\u003c/u\u003e All\u003cu\u003ea\u003c/u\u003ehu AAamalakum warasooluhu thumma turaddoona il\u003cu\u003ea\u003c/u\u003e AA\u003cu\u003ea\u003c/u\u003elimi alghaybi wa\u003cb\u003eal\u003c/b\u003eshshah\u003cu\u003ea\u003c/u\u003edati fayunabbiokum bim\u003cu\u003ea\u003c/u\u003e kuntum taAAmaloon\u003cb\u003ea\u003c/b\u003e"
    },
    {
        "BookCode":  "TLT",
        "SurahNumber":  "9",
        "AyahNumber":  "95",
        "Recitation":  "Alafasy_128kbps/009095",
        "Body":  "Saya\u003cu\u003eh\u003c/u\u003elifoona bi\u003cb\u003eA\u003c/b\u003ell\u003cu\u003ea\u003c/u\u003ehi lakum i\u003cu\u003etha\u003c/u\u003e inqalabtum ilayhim lituAAri\u003cu\u003ed\u003c/u\u003eoo AAanhum faaAAri\u003cu\u003ed\u003c/u\u003eoo AAanhum innahum rijsun wamaw\u003cu\u003ea\u003c/u\u003ehum jahannamu jaz\u003cu\u003ea\u003c/u\u003ean bim\u003cu\u003ea\u003c/u\u003e k\u003cu\u003ea\u003c/u\u003enoo yaksiboon\u003cb\u003ea\u003c/b\u003e"
    },
    {
        "BookCode":  "TLT",
        "SurahNumber":  "9",
        "AyahNumber":  "96",
        "Recitation":  "Alafasy_128kbps/009096",
        "Body":  "Ya\u003cu\u003eh\u003c/u\u003elifoona lakum litar\u003cu\u003ed\u003c/u\u003eaw AAanhum fain tar\u003cu\u003ed\u003c/u\u003eaw AAanhum fainna All\u003cu\u003ea\u003c/u\u003eha l\u003cu\u003ea\u003c/u\u003e yar\u003cu\u003eda\u003c/u\u003e AAani alqawmi alf\u003cu\u003ea\u003c/u\u003esiqeen\u003cb\u003ea\u003c/b\u003e"
    },
    {
        "BookCode":  "TLT",
        "SurahNumber":  "9",
        "AyahNumber":  "97",
        "Recitation":  "Alafasy_128kbps/009097",
        "Body":  "AlaAAr\u003cu\u003ea\u003c/u\u003ebu ashaddu kufran wanif\u003cu\u003ea\u003c/u\u003eqan waajdaru all\u003cu\u003ea\u003c/u\u003e yaAAlamoo \u003cu\u003eh\u003c/u\u003eudooda m\u003cu\u003ea\u003c/u\u003e anzala All\u003cu\u003ea\u003c/u\u003ehu AAal\u003cu\u003ea\u003c/u\u003e rasoolihi wa\u003cb\u003eA\u003c/b\u003ell\u003cu\u003ea\u003c/u\u003ehu AAaleemun \u003cu\u003eh\u003c/u\u003eakeem\u003cb\u003eun\u003c/b\u003e"
    },
    {
        "BookCode":  "TLT",
        "SurahNumber":  "9",
        "AyahNumber":  "98",
        "Recitation":  "Alafasy_128kbps/009098",
        "Body":  "Wamina alaAAr\u003cu\u003ea\u003c/u\u003ebi man yattakhi\u003cu\u003eth\u003c/u\u003eu m\u003cu\u003ea\u003c/u\u003e yunfiqu maghraman wayatarabba\u003cu\u003es\u003c/u\u003eu bikumu a\u003cb\u003el\u003c/b\u003eddaw\u003cu\u003ea\u003c/u\u003eira AAalayhim d\u003cu\u003ea\u003c/u\u003eiratu a\u003cb\u003el\u003c/b\u003essawi wa\u003cb\u003eA\u003c/b\u003ell\u003cu\u003ea\u003c/u\u003ehu sameeAAun AAaleem\u003cb\u003eun\u003c/b\u003e"
    },
    {
        "BookCode":  "TLT",
        "SurahNumber":  "9",
        "AyahNumber":  "99",
        "Recitation":  "Alafasy_128kbps/009099",
        "Body":  "Wamina alaAAr\u003cu\u003ea\u003c/u\u003ebi man yuminu bi\u003cb\u003eA\u003c/b\u003ell\u003cu\u003ea\u003c/u\u003ehi wa\u003cb\u003ea\u003c/b\u003elyawmi al\u003cu\u003ea\u003c/u\u003ekhiri wayattakhi\u003cu\u003eth\u003c/u\u003eu m\u003cu\u003ea\u003c/u\u003e yunfiqu qurub\u003cu\u003ea\u003c/u\u003etin AAinda All\u003cu\u003ea\u003c/u\u003ehi wa\u003cu\u003es\u003c/u\u003ealaw\u003cu\u003ea\u003c/u\u003eti a\u003cb\u003el\u003c/b\u003errasooli al\u003cu\u003ea\u003c/u\u003e innah\u003cu\u003ea\u003c/u\u003e qurbatun lahum sayudkhiluhumu All\u003cu\u003ea\u003c/u\u003ehu fee ra\u003cu\u003eh\u003c/u\u003ematihi inna All\u003cu\u003ea\u003c/u\u003eha ghafoorun ra\u003cu\u003eh\u003c/u\u003eeem\u003cb\u003eun\u003c/b\u003e"
    }
]
