[
    {
        "BookCode":  "MAL",
        "SurahNumber":  "106",
        "AyahNumber":  "1",
        "Recitation":  "Alafasy_128kbps/106001",
        "Body":  "The privilege of protection enjoyed by the Qureysh,"
    },
    {
        "BookCode":  "MAL",
        "SurahNumber":  "106",
        "AyahNumber":  "2",
        "Recitation":  "Alafasy_128kbps/106002",
        "Body":  "safe passage of their trading caravans in the winter and the\n\t\t\tsummer (due to their being the caretakers of the House of Allah,\n\t\t\tand they know this fact),"
    },
    {
        "BookCode":  "MAL",
        "SurahNumber":  "106",
        "AyahNumber":  "3",
        "Recitation":  "Alafasy_128kbps/106003",
        "Body":  "So they should worship the Rabb of this House,"
    },
    {
        "BookCode":  "MAL",
        "SurahNumber":  "106",
        "AyahNumber":  "4",
        "Recitation":  "Alafasy_128kbps/106004",
        "Body":  "Who provided them food in the days of famine and made them secure\n\t\t\tagainst fear."
    }
]
