[
    {
        "BookCode":  "PIK",
        "SurahNumber":  "43",
        "AyahNumber":  "1",
        "Recitation":  "Alafasy_128kbps/043001",
        "Body":  "Ha. Mim."
    },
    {
        "BookCode":  "PIK",
        "SurahNumber":  "43",
        "AyahNumber":  "10",
        "Recitation":  "Alafasy_128kbps/043010",
        "Body":  "Who made the earth a resting place for you, and placed roads for\n\t\t\tyou therein, that haply ye may find your way;"
    },
    {
        "BookCode":  "PIK",
        "SurahNumber":  "43",
        "AyahNumber":  "11",
        "Recitation":  "Alafasy_128kbps/043011",
        "Body":  "And who sendeth down water from the sky in (due) measure, and We\n\t\t\trevive a dead land therewith. Even so will ye be brought forth;"
    },
    {
        "BookCode":  "PIK",
        "SurahNumber":  "43",
        "AyahNumber":  "12",
        "Recitation":  "Alafasy_128kbps/043012",
        "Body":  "He who created all the pairs, and appointed for you ships and\n\t\t\tcattle whereupon ye ride."
    },
    {
        "BookCode":  "PIK",
        "SurahNumber":  "43",
        "AyahNumber":  "13",
        "Recitation":  "Alafasy_128kbps/043013",
        "Body":  "That ye may mount upon their backs, and may remember your Lord\u0027s\n\t\t\tfavor when ye mount thereon, and may say: Glorified be He Who\n\t\t\thath subdued these unto us, and we were not capable (of subduing\n\t\t\tthem);"
    },
    {
        "BookCode":  "PIK",
        "SurahNumber":  "43",
        "AyahNumber":  "14",
        "Recitation":  "Alafasy_128kbps/043014",
        "Body":  "And lo! unto our Lord we are returning."
    },
    {
        "BookCode":  "PIK",
        "SurahNumber":  "43",
        "AyahNumber":  "15",
        "Recitation":  "Alafasy_128kbps/043015",
        "Body":  "And they allot to Him a portion of His bondmen! Lo! man is verily\n\t\t\ta mere ingrate."
    },
    {
        "BookCode":  "PIK",
        "SurahNumber":  "43",
        "AyahNumber":  "16",
        "Recitation":  "Alafasy_128kbps/043016",
        "Body":  "Or chooseth He daughters of all that He hath created, and\n\t\t\thonoureth He you with sons?"
    },
    {
        "BookCode":  "PIK",
        "SurahNumber":  "43",
        "AyahNumber":  "17",
        "Recitation":  "Alafasy_128kbps/043017",
        "Body":  "And if one of them hath tidings of that which he likeneth to the\n\t\t\tBeneficent One, his countenance becometh black and he is full of\n\t\t\tinward rage."
    },
    {
        "BookCode":  "PIK",
        "SurahNumber":  "43",
        "AyahNumber":  "18",
        "Recitation":  "Alafasy_128kbps/043018",
        "Body":  "(Liken they then to Allah) that which is bred up in outward show,\n\t\t\tand in dispute cannot make itself plain?"
    },
    {
        "BookCode":  "PIK",
        "SurahNumber":  "43",
        "AyahNumber":  "19",
        "Recitation":  "Alafasy_128kbps/043019",
        "Body":  "And they make the angels, who are the slaves of the Beneficent,\n\t\t\tfemales. Did they witness their creation? Their testimony will be\n\t\t\trecorded and they will be questioned."
    },
    {
        "BookCode":  "PIK",
        "SurahNumber":  "43",
        "AyahNumber":  "2",
        "Recitation":  "Alafasy_128kbps/043002",
        "Body":  "By the Scripture which maketh plain,"
    },
    {
        "BookCode":  "PIK",
        "SurahNumber":  "43",
        "AyahNumber":  "20",
        "Recitation":  "Alafasy_128kbps/043020",
        "Body":  "And they say: If the Beneficent One had (so) willed, we should\n\t\t\tnot have worshipped them. They have no knowledge whatsoever of\n\t\t\tthat. They do but guess."
    },
    {
        "BookCode":  "PIK",
        "SurahNumber":  "43",
        "AyahNumber":  "21",
        "Recitation":  "Alafasy_128kbps/043021",
        "Body":  "Or have We given them any Scripture before (this Qur\u0027an) so that\n\t\t\tthey are holding fast thereto?"
    },
    {
        "BookCode":  "PIK",
        "SurahNumber":  "43",
        "AyahNumber":  "22",
        "Recitation":  "Alafasy_128kbps/043022",
        "Body":  "Nay, for they say only: Lo! we found our fathers following a\n\t\t\treligion, and we are guided by their footprints."
    },
    {
        "BookCode":  "PIK",
        "SurahNumber":  "43",
        "AyahNumber":  "23",
        "Recitation":  "Alafasy_128kbps/043023",
        "Body":  "And even so We sent not a warner before thee (Muhammad) into any\n\t\t\ttownship but its luxurious ones said: Lo! we found our fathers\n\t\t\tfollowing a religion, and we are following their footprints."
    },
    {
        "BookCode":  "PIK",
        "SurahNumber":  "43",
        "AyahNumber":  "24",
        "Recitation":  "Alafasy_128kbps/043024",
        "Body":  "(And the warner) said: What! Even though I bring you better\n\t\t\tguidance than that ye found your fathers following? They\n\t\t\tanswered: Lo! in what ye bring we are disbelievers."
    },
    {
        "BookCode":  "PIK",
        "SurahNumber":  "43",
        "AyahNumber":  "25",
        "Recitation":  "Alafasy_128kbps/043025",
        "Body":  "So We requited them. Then see the nature of the consequence for\n\t\t\tthe rejecters!"
    },
    {
        "BookCode":  "PIK",
        "SurahNumber":  "43",
        "AyahNumber":  "26",
        "Recitation":  "Alafasy_128kbps/043026",
        "Body":  "And when Abraham said unto his father and his folk: Lo! I am\n\t\t\tinnocent of what ye worship"
    },
    {
        "BookCode":  "PIK",
        "SurahNumber":  "43",
        "AyahNumber":  "27",
        "Recitation":  "Alafasy_128kbps/043027",
        "Body":  "Save Him Who did create me, for He will surely guide me."
    },
    {
        "BookCode":  "PIK",
        "SurahNumber":  "43",
        "AyahNumber":  "28",
        "Recitation":  "Alafasy_128kbps/043028",
        "Body":  "And he made It a word enduring among his seed, that haply they\n\t\t\tmight return."
    },
    {
        "BookCode":  "PIK",
        "SurahNumber":  "43",
        "AyahNumber":  "29",
        "Recitation":  "Alafasy_128kbps/043029",
        "Body":  "Nay, but I let these and their fathers enjoy life (only) till\n\t\t\tthere should come unto them the Truth and a messenger making\n\t\t\tplain."
    },
    {
        "BookCode":  "PIK",
        "SurahNumber":  "43",
        "AyahNumber":  "3",
        "Recitation":  "Alafasy_128kbps/043003",
        "Body":  "Lo! We have appointed it a Lecture in Arabic that haply ye may\n\t\t\tunderstand."
    },
    {
        "BookCode":  "PIK",
        "SurahNumber":  "43",
        "AyahNumber":  "30",
        "Recitation":  "Alafasy_128kbps/043030",
        "Body":  "And now that the Truth hath come unto them they say: This is mere\n\t\t\tmagic, and lo! we are disbelievers therein."
    },
    {
        "BookCode":  "PIK",
        "SurahNumber":  "43",
        "AyahNumber":  "31",
        "Recitation":  "Alafasy_128kbps/043031",
        "Body":  "And they say: If only this Qur\u0027an had been revealed to some great\n\t\t\tman of the two towns?"
    },
    {
        "BookCode":  "PIK",
        "SurahNumber":  "43",
        "AyahNumber":  "32",
        "Recitation":  "Alafasy_128kbps/043032",
        "Body":  "Is it they who apportion their Lord\u0027s mercy? We have apportioned\n\t\t\tamong them their livelihood in the life of the world, and raised\n\t\t\tsome of them above others in rank that some of them may take\n\t\t\tlabor from others; and the mercy of thy Lord is better than (the\n\t\t\twealth) that they amass."
    },
    {
        "BookCode":  "PIK",
        "SurahNumber":  "43",
        "AyahNumber":  "33",
        "Recitation":  "Alafasy_128kbps/043033",
        "Body":  "And were it not that mankind would have become one community, We\n\t\t\tmight well have appointed, for those who disbelieve in the\n\t\t\tBeneficent, roofs of silver for their houses and stairs (of\n\t\t\tsilver) whereby to mount,"
    },
    {
        "BookCode":  "PIK",
        "SurahNumber":  "43",
        "AyahNumber":  "34",
        "Recitation":  "Alafasy_128kbps/043034",
        "Body":  "And for their houses doors (of silver) and couches of silver\n\t\t\twhereon to recline,"
    },
    {
        "BookCode":  "PIK",
        "SurahNumber":  "43",
        "AyahNumber":  "35",
        "Recitation":  "Alafasy_128kbps/043035",
        "Body":  "And ornaments of gold. Yet all that would have been but a\n\t\t\tprovision of the life of the world. And the Hereafter with your\n\t\t\tLord would have been for those who keep from evil."
    },
    {
        "BookCode":  "PIK",
        "SurahNumber":  "43",
        "AyahNumber":  "36",
        "Recitation":  "Alafasy_128kbps/043036",
        "Body":  "And he whose sight is dim to the remembrance of the Beneficent,\n\t\t\tWe assign unto him a devil who becometh his comrade;"
    },
    {
        "BookCode":  "PIK",
        "SurahNumber":  "43",
        "AyahNumber":  "37",
        "Recitation":  "Alafasy_128kbps/043037",
        "Body":  "And lo! they surely turn them from the way of Allah, and yet they\n\t\t\tdeem that they are rightly guided;"
    },
    {
        "BookCode":  "PIK",
        "SurahNumber":  "43",
        "AyahNumber":  "38",
        "Recitation":  "Alafasy_128kbps/043038",
        "Body":  "Till, when he cometh unto Us, he saith (unto his comrade): Ah,\n\t\t\twould that between me and thee there were the distance of the two\n\t\t\thorizons--an evil comrade!"
    },
    {
        "BookCode":  "PIK",
        "SurahNumber":  "43",
        "AyahNumber":  "39",
        "Recitation":  "Alafasy_128kbps/043039",
        "Body":  "And it profiteth you not this day, because ye did wrong, that ye\n\t\t\twill be sharers in the doom."
    },
    {
        "BookCode":  "PIK",
        "SurahNumber":  "43",
        "AyahNumber":  "4",
        "Recitation":  "Alafasy_128kbps/043004",
        "Body":  "And lo! in the Source of Decrees, which We possess, it is indeed\n\t\t\tsublime, decisive,"
    },
    {
        "BookCode":  "PIK",
        "SurahNumber":  "43",
        "AyahNumber":  "40",
        "Recitation":  "Alafasy_128kbps/043040",
        "Body":  "Canst thou (Muhammad) make the deaf to hear, or canst thou guide\n\t\t\tthe blind or him who is in error manifest?"
    },
    {
        "BookCode":  "PIK",
        "SurahNumber":  "43",
        "AyahNumber":  "41",
        "Recitation":  "Alafasy_128kbps/043041",
        "Body":  "And if We take thee away, We surely shall take vengeance on them;"
    },
    {
        "BookCode":  "PIK",
        "SurahNumber":  "43",
        "AyahNumber":  "42",
        "Recitation":  "Alafasy_128kbps/043042",
        "Body":  "Or (if) We show thee that wherewith We threaten them; for lo! We\n\t\t\thave complete command of them."
    },
    {
        "BookCode":  "PIK",
        "SurahNumber":  "43",
        "AyahNumber":  "43",
        "Recitation":  "Alafasy_128kbps/043043",
        "Body":  "So hold thou fast to that which is inspired in thee. Lo! thou art\n\t\t\ton a right path."
    },
    {
        "BookCode":  "PIK",
        "SurahNumber":  "43",
        "AyahNumber":  "44",
        "Recitation":  "Alafasy_128kbps/043044",
        "Body":  "And lo! it is in truth a Reminder for thee and for thy folk; and\n\t\t\tye will be questioned."
    },
    {
        "BookCode":  "PIK",
        "SurahNumber":  "43",
        "AyahNumber":  "45",
        "Recitation":  "Alafasy_128kbps/043045",
        "Body":  "And ask those of Our messengers whom We sent before thee: Did We\n\t\t\tever appoint gods to be worshipped beside the Beneficent?"
    },
    {
        "BookCode":  "PIK",
        "SurahNumber":  "43",
        "AyahNumber":  "46",
        "Recitation":  "Alafasy_128kbps/043046",
        "Body":  "And verily We sent Moses with Our revelations unto Pharaoh and\n\t\t\this chiefs, and he said: I am a messenger of the Lord of the\n\t\t\tWorlds."
    },
    {
        "BookCode":  "PIK",
        "SurahNumber":  "43",
        "AyahNumber":  "47",
        "Recitation":  "Alafasy_128kbps/043047",
        "Body":  "But when he brought them Our tokens, behold! they laughed at\n\t\t\tthem."
    },
    {
        "BookCode":  "PIK",
        "SurahNumber":  "43",
        "AyahNumber":  "48",
        "Recitation":  "Alafasy_128kbps/043048",
        "Body":  "And every token that We showed them was greater than its sister\n\t\t\t(token), and we grasped them with the torment, that haply they\n\t\t\tmight turn again."
    },
    {
        "BookCode":  "PIK",
        "SurahNumber":  "43",
        "AyahNumber":  "49",
        "Recitation":  "Alafasy_128kbps/043049",
        "Body":  "And they said: O wizard; Entreat thy Lord for us by the pact that\n\t\t\tHe hath made with thee. Lo! we verily will walk aright."
    },
    {
        "BookCode":  "PIK",
        "SurahNumber":  "43",
        "AyahNumber":  "5",
        "Recitation":  "Alafasy_128kbps/043005",
        "Body":  "Shall We utterly ignore you because ye are a wanton folk?"
    },
    {
        "BookCode":  "PIK",
        "SurahNumber":  "43",
        "AyahNumber":  "50",
        "Recitation":  "Alafasy_128kbps/043050",
        "Body":  "But when We eased them of the torment, behold! they broke their\n\t\t\tword."
    },
    {
        "BookCode":  "PIK",
        "SurahNumber":  "43",
        "AyahNumber":  "51",
        "Recitation":  "Alafasy_128kbps/043051",
        "Body":  "And Pharaoh caused a proclamation to be made among his people\n\t\t\tsaying: O my people! Is not mine the sovereignty of Egypt and\n\t\t\tthese rivers flowing under me? Can ye not then discern?"
    },
    {
        "BookCode":  "PIK",
        "SurahNumber":  "43",
        "AyahNumber":  "52",
        "Recitation":  "Alafasy_128kbps/043052",
        "Body":  "I am surely better than this fellow, who is despicable, and can\n\t\t\thardly make (his meaning) plain!"
    },
    {
        "BookCode":  "PIK",
        "SurahNumber":  "43",
        "AyahNumber":  "53",
        "Recitation":  "Alafasy_128kbps/043053",
        "Body":  "Why, then, have armlets of gold not been set upon him, or angels\n\t\t\tsent along with him?"
    },
    {
        "BookCode":  "PIK",
        "SurahNumber":  "43",
        "AyahNumber":  "54",
        "Recitation":  "Alafasy_128kbps/043054",
        "Body":  "Thus he persuaded his people to make light (of Moses), and they\n\t\t\tobeyed him. Lo! they were a wanton folk."
    },
    {
        "BookCode":  "PIK",
        "SurahNumber":  "43",
        "AyahNumber":  "55",
        "Recitation":  "Alafasy_128kbps/043055",
        "Body":  "So, when they angered Us, We punished them and drowned them every\n\t\t\tone."
    },
    {
        "BookCode":  "PIK",
        "SurahNumber":  "43",
        "AyahNumber":  "56",
        "Recitation":  "Alafasy_128kbps/043056",
        "Body":  "And We made them a thing past, and an example for those after\n\t\t\t(them)."
    },
    {
        "BookCode":  "PIK",
        "SurahNumber":  "43",
        "AyahNumber":  "57",
        "Recitation":  "Alafasy_128kbps/043057",
        "Body":  "And when the son of Mary is quoted as an example, behold! the\n\t\t\tfolk laugh out,"
    },
    {
        "BookCode":  "PIK",
        "SurahNumber":  "43",
        "AyahNumber":  "58",
        "Recitation":  "Alafasy_128kbps/043058",
        "Body":  "And say: Are our gods better, or is he? They raise not the\n\t\t\tobjection save for argument. Nay! but they are a contentious\n\t\t\tfolk."
    },
    {
        "BookCode":  "PIK",
        "SurahNumber":  "43",
        "AyahNumber":  "59",
        "Recitation":  "Alafasy_128kbps/043059",
        "Body":  "He is nothing but a slave on whom We bestowed favor, and We made\n\t\t\thim a pattern for the Children of Israel."
    },
    {
        "BookCode":  "PIK",
        "SurahNumber":  "43",
        "AyahNumber":  "6",
        "Recitation":  "Alafasy_128kbps/043006",
        "Body":  "How many a Prophet did We send among the men of old!"
    },
    {
        "BookCode":  "PIK",
        "SurahNumber":  "43",
        "AyahNumber":  "60",
        "Recitation":  "Alafasy_128kbps/043060",
        "Body":  "And had We willed We could have set among you angels to be\n\t\t\tviceroys in the earth."
    },
    {
        "BookCode":  "PIK",
        "SurahNumber":  "43",
        "AyahNumber":  "61",
        "Recitation":  "Alafasy_128kbps/043061",
        "Body":  "And lo! verily there is knowledge of the Hour. So doubt ye not\n\t\t\tconcerning it, but follow Me. This is the right path."
    },
    {
        "BookCode":  "PIK",
        "SurahNumber":  "43",
        "AyahNumber":  "62",
        "Recitation":  "Alafasy_128kbps/043062",
        "Body":  "And let not Satan turn you aside. Lo! he is an open enemy for\n\t\t\tyou."
    },
    {
        "BookCode":  "PIK",
        "SurahNumber":  "43",
        "AyahNumber":  "63",
        "Recitation":  "Alafasy_128kbps/043063",
        "Body":  "When Jesus came with clear proofs (of Allah\u0027s sovereignty), he\n\t\t\tsaid: I have come unto you with wisdom, and to make plain some of\n\t\t\tthat concerning which ye differ. So keep your duty to Allah, and\n\t\t\tobey me."
    },
    {
        "BookCode":  "PIK",
        "SurahNumber":  "43",
        "AyahNumber":  "64",
        "Recitation":  "Alafasy_128kbps/043064",
        "Body":  "Lo! Allah, He is my Lord and your Lord. So worship Him. This is a\n\t\t\tright path."
    },
    {
        "BookCode":  "PIK",
        "SurahNumber":  "43",
        "AyahNumber":  "65",
        "Recitation":  "Alafasy_128kbps/043065",
        "Body":  "But the factions among them differed. Then woe unto those who do\n\t\t\twrong from the doom of a painful day."
    },
    {
        "BookCode":  "PIK",
        "SurahNumber":  "43",
        "AyahNumber":  "66",
        "Recitation":  "Alafasy_128kbps/043066",
        "Body":  "Await they aught save the Hour, that it shall come upon them\n\t\t\tsuddenly, when they know not?"
    },
    {
        "BookCode":  "PIK",
        "SurahNumber":  "43",
        "AyahNumber":  "67",
        "Recitation":  "Alafasy_128kbps/043067",
        "Body":  "Friends on that day will be foes one to another, save those who\n\t\t\tkept their duty (to Allah)."
    },
    {
        "BookCode":  "PIK",
        "SurahNumber":  "43",
        "AyahNumber":  "68",
        "Recitation":  "Alafasy_128kbps/043068",
        "Body":  "O My slaves! For you there is no fear this day, nor is it ye who\n\t\t\tgrieve;"
    },
    {
        "BookCode":  "PIK",
        "SurahNumber":  "43",
        "AyahNumber":  "69",
        "Recitation":  "Alafasy_128kbps/043069",
        "Body":  "(Ye) who believed Our revelations and were self-surrendered,"
    },
    {
        "BookCode":  "PIK",
        "SurahNumber":  "43",
        "AyahNumber":  "7",
        "Recitation":  "Alafasy_128kbps/043007",
        "Body":  "And never came there unto them a Prophet but they used to mock\n\t\t\thim."
    },
    {
        "BookCode":  "PIK",
        "SurahNumber":  "43",
        "AyahNumber":  "70",
        "Recitation":  "Alafasy_128kbps/043070",
        "Body":  "Enter the Garden, ye and your wives, to be made glad."
    },
    {
        "BookCode":  "PIK",
        "SurahNumber":  "43",
        "AyahNumber":  "71",
        "Recitation":  "Alafasy_128kbps/043071",
        "Body":  "Therein are brought round for them trays of gold and goblets, and\n\t\t\ttherein is all that souls desire and eyes find sweet. And ye are\n\t\t\timmortal therein."
    },
    {
        "BookCode":  "PIK",
        "SurahNumber":  "43",
        "AyahNumber":  "72",
        "Recitation":  "Alafasy_128kbps/043072",
        "Body":  "This is the Garden which ye are made to inherit because of what\n\t\t\tye used to do."
    },
    {
        "BookCode":  "PIK",
        "SurahNumber":  "43",
        "AyahNumber":  "73",
        "Recitation":  "Alafasy_128kbps/043073",
        "Body":  "Therein for you is fruit in plenty whence to eat."
    },
    {
        "BookCode":  "PIK",
        "SurahNumber":  "43",
        "AyahNumber":  "74",
        "Recitation":  "Alafasy_128kbps/043074",
        "Body":  "Lo! the guilty are immortal in hell\u0027s torment."
    },
    {
        "BookCode":  "PIK",
        "SurahNumber":  "43",
        "AyahNumber":  "75",
        "Recitation":  "Alafasy_128kbps/043075",
        "Body":  "It is not relaxed for them, and they despair therein."
    },
    {
        "BookCode":  "PIK",
        "SurahNumber":  "43",
        "AyahNumber":  "76",
        "Recitation":  "Alafasy_128kbps/043076",
        "Body":  "We wronged them not, but they it was who did the wrong."
    },
    {
        "BookCode":  "PIK",
        "SurahNumber":  "43",
        "AyahNumber":  "77",
        "Recitation":  "Alafasy_128kbps/043077",
        "Body":  "And they cry: O master! Let thy Lord make an end of us. He saith:\n\t\t\tLo! here ye must remain."
    },
    {
        "BookCode":  "PIK",
        "SurahNumber":  "43",
        "AyahNumber":  "78",
        "Recitation":  "Alafasy_128kbps/043078",
        "Body":  "We verily brought the Truth unto you, but ye were, most of you,\n\t\t\taverse to the Truth."
    },
    {
        "BookCode":  "PIK",
        "SurahNumber":  "43",
        "AyahNumber":  "79",
        "Recitation":  "Alafasy_128kbps/043079",
        "Body":  "Or do they determine any thing (against the Prophet)? Lo! We\n\t\t\t(also) are determining."
    },
    {
        "BookCode":  "PIK",
        "SurahNumber":  "43",
        "AyahNumber":  "8",
        "Recitation":  "Alafasy_128kbps/043008",
        "Body":  "Then we destroyed men mightier than these in prowess; and the\n\t\t\texample of the men of old hath gone (before them)."
    },
    {
        "BookCode":  "PIK",
        "SurahNumber":  "43",
        "AyahNumber":  "80",
        "Recitation":  "Alafasy_128kbps/043080",
        "Body":  "Or deem they that We cannot hear their secret thoughts and\n\t\t\tprivate confidences? Nay, but Our envoys, present with them, do\n\t\t\trecord."
    },
    {
        "BookCode":  "PIK",
        "SurahNumber":  "43",
        "AyahNumber":  "81",
        "Recitation":  "Alafasy_128kbps/043081",
        "Body":  "Say (O Muhammad): The Beneficent One hath no son. I am first\n\t\t\tamong the worshippers."
    },
    {
        "BookCode":  "PIK",
        "SurahNumber":  "43",
        "AyahNumber":  "82",
        "Recitation":  "Alafasy_128kbps/043082",
        "Body":  "Glorified be the Lord of the heavens and the earth, the Lord of\n\t\t\tthe Throne, from that which they ascribe (unto Him)!"
    },
    {
        "BookCode":  "PIK",
        "SurahNumber":  "43",
        "AyahNumber":  "83",
        "Recitation":  "Alafasy_128kbps/043083",
        "Body":  "So let them flounder (in their talk) and play until they meet the\n\t\t\tDay which they are promised."
    },
    {
        "BookCode":  "PIK",
        "SurahNumber":  "43",
        "AyahNumber":  "84",
        "Recitation":  "Alafasy_128kbps/043084",
        "Body":  "And He it is Who in the heaven is God, and in the earth God. He\n\t\t\tis the Wise, the knower."
    },
    {
        "BookCode":  "PIK",
        "SurahNumber":  "43",
        "AyahNumber":  "85",
        "Recitation":  "Alafasy_128kbps/043085",
        "Body":  "And blessed be He unto Whom belongeth the Sovereignty of the\n\t\t\theavens and the earth and all that is between them, and with Whom\n\t\t\tis knowledge of the Hour, and unto Whom ye will be returned."
    },
    {
        "BookCode":  "PIK",
        "SurahNumber":  "43",
        "AyahNumber":  "86",
        "Recitation":  "Alafasy_128kbps/043086",
        "Body":  "And those unto whom they cry instead of Him possess no power of\n\t\t\tintercession, saving him who beareth witness unto the Truth\n\t\t\tknowingly."
    },
    {
        "BookCode":  "PIK",
        "SurahNumber":  "43",
        "AyahNumber":  "87",
        "Recitation":  "Alafasy_128kbps/043087",
        "Body":  "And if thou ask them who created them, they will surely say:\n\t\t\tAllah. How then are they turned away?"
    },
    {
        "BookCode":  "PIK",
        "SurahNumber":  "43",
        "AyahNumber":  "88",
        "Recitation":  "Alafasy_128kbps/043088",
        "Body":  "And he saith: O my Lord! Lo! those are a folk who believe not."
    },
    {
        "BookCode":  "PIK",
        "SurahNumber":  "43",
        "AyahNumber":  "89",
        "Recitation":  "Alafasy_128kbps/043089",
        "Body":  "Then bear with them (O Muhammad) and say: Peace. But they will\n\t\t\tcome to know."
    },
    {
        "BookCode":  "PIK",
        "SurahNumber":  "43",
        "AyahNumber":  "9",
        "Recitation":  "Alafasy_128kbps/043009",
        "Body":  "And if thou (Muhammad) ask them: Who created the heavens and the\n\t\t\tearth, they will surely answer: The Mighty, the Knower created\n\t\t\tthem;"
    }
]
